{"h241": {"h231": {"s3": {"s23": ["s24:ingress7", "s24:egress1", "s3:ingress18", "s3:egress3", "s9:ingress1", "s9:egress6", "s8:ingress3", "s8:egress17", "s23:ingress6", "s23:egress7"]}, "s24": {"s3": ["s24:ingress7", "s24:egress6", "s8:ingress18", "s8:egress17", "s23:ingress6", "s23:egress7"]}}, "h171": {"s3": {"s17": ["s24:ingress7", "s24:egress1", "s3:ingress18", "s3:egress3", "s9:ingress1", "s9:egress6", "s8:ingress3", "s8:egress11", "s17:ingress6", "s17:egress7"]}, "s24": {"s3": ["s24:ingress7", "s24:egress6", "s8:ingress18", "s8:egress11", "s17:ingress6", "s17:egress7"]}}, "h111": {"s3": {"s11": ["s24:ingress7", "s24:egress1", "s3:ingress18", "s3:egress3", "s9:ingress1", "s9:egress6", "s8:ingress3", "s8:egress5", "s11:ingress6", "s11:egress7"]}, "s24": {"s3": ["s24:ingress7", "s24:egress6", "s8:ingress18", "s8:egress5", "s11:ingress6", "s11:egress7"]}}, "h131": {"s3": {"s13": ["s24:ingress7", "s24:egress1", "s3:ingress18", "s3:egress3", "s9:ingress1", "s9:egress6", "s8:ingress3", "s8:egress7", "s13:ingress6", "s13:egress7"]}, "s24": {"s3": ["s24:ingress7", "s24:egress6", "s8:ingress18", "s8:egress7", "s13:ingress6", "s13:egress7"]}}, "h121": {"s3": {"s12": ["s24:ingress7", "s24:egress1", "s3:ingress18", "s3:egress3", "s9:ingress1", "s9:egress6", "s8:ingress3", "s8:egress6", "s12:ingress6", "s12:egress7"]}, "s24": {"s3": ["s24:ingress7", "s24:egress6", "s8:ingress18", "s8:egress6", "s12:ingress6", "s12:egress7"]}}, "h261": {"s3": {"s26": ["s24:ingress7", "s24:egress1", "s3:ingress18", "s3:egress3", "s9:ingress1", "s9:egress6", "s8:ingress3", "s8:egress20", "s26:ingress6", "s26:egress7"]}, "s24": {"s3": ["s24:ingress7", "s24:egress6", "s8:ingress18", "s8:egress20", "s26:ingress6", "s26:egress7"]}}, "h91": {"s3": {"s9": ["s24:ingress7", "s24:egress1", "s3:ingress18", "s3:egress12", "s18:ingress1", "s18:egress6", "s8:ingress12", "s8:egress3", "s9:ingress6", "s9:egress7"]}, "s24": {"s3": ["s24:ingress7", "s24:egress6", "s8:ingress18", "s8:egress3", "s9:ingress6", "s9:egress7"]}}, "h161": {"s3": {"s16": ["s24:ingress7", "s24:egress1", "s3:ingress18", "s3:egress3", "s9:ingress1", "s9:egress6", "s8:ingress3", "s8:egress10", "s16:ingress6", "s16:egress7"]}, "s24": {"s3": ["s24:ingress7", "s24:egress6", "s8:ingress18", "s8:egress10", "s16:ingress6", "s16:egress7"]}}, "h191": {"s3": {"s19": ["s24:ingress7", "s24:egress1", "s3:ingress18", "s3:egress3", "s9:ingress1", "s9:egress6", "s8:ingress3", "s8:egress13", "s19:ingress6", "s19:egress7"]}, "s24": {"s3": ["s24:ingress7", "s24:egress6", "s8:ingress18", "s8:egress13", "s19:ingress6", "s19:egress7"]}}, "h101": {"s3": {"s10": ["s24:ingress7", "s24:egress1", "s3:ingress18", "s3:egress3", "s9:ingress1", "s9:egress6", "s8:ingress3", "s8:egress4", "s10:ingress6", "s10:egress7"]}, "s24": {"s3": ["s24:ingress7", "s24:egress6", "s8:ingress18", "s8:egress4", "s10:ingress6", "s10:egress7"]}}, "h221": {"s3": {"s22": ["s24:ingress7", "s24:egress1", "s3:ingress18", "s3:egress3", "s9:ingress1", "s9:egress6", "s8:ingress3", "s8:egress16", "s22:ingress6", "s22:egress7"]}, "s24": {"s3": ["s24:ingress7", "s24:egress6", "s8:ingress18", "s8:egress16", "s22:ingress6", "s22:egress7"]}}, "h141": {"s3": {"s14": ["s24:ingress7", "s24:egress1", "s3:ingress18", "s3:egress3", "s9:ingress1", "s9:egress6", "s8:ingress3", "s8:egress8", "s14:ingress6", "s14:egress7"]}, "s24": {"s3": ["s24:ingress7", "s24:egress6", "s8:ingress18", "s8:egress8", "s14:ingress6", "s14:egress7"]}}, "h251": {"s3": {"s25": ["s24:ingress7", "s24:egress1", "s3:ingress18", "s3:egress3", "s9:ingress1", "s9:egress6", "s8:ingress3", "s8:egress19", "s25:ingress6", "s25:egress7"]}, "s24": {"s3": ["s24:ingress7", "s24:egress6", "s8:ingress18", "s8:egress19", "s25:ingress6", "s25:egress7"]}}, "h201": {"s3": {"s20": ["s24:ingress7", "s24:egress1", "s3:ingress18", "s3:egress3", "s9:ingress1", "s9:egress6", "s8:ingress3", "s8:egress14", "s20:ingress6", "s20:egress7"]}, "s24": {"s3": ["s24:ingress7", "s24:egress6", "s8:ingress18", "s8:egress14", "s20:ingress6", "s20:egress7"]}}, "h181": {"s3": {"s18": ["s24:ingress7", "s24:egress1", "s3:ingress18", "s3:egress3", "s9:ingress1", "s9:egress6", "s8:ingress3", "s8:egress12", "s18:ingress6", "s18:egress7"]}, "s24": {"s3": ["s24:ingress7", "s24:egress6", "s8:ingress18", "s8:egress12", "s18:ingress6", "s18:egress7"]}}, "h211": {"s3": {"s21": ["s24:ingress7", "s24:egress1", "s3:ingress18", "s3:egress3", "s9:ingress1", "s9:egress6", "s8:ingress3", "s8:egress15", "s21:ingress6", "s21:egress7"]}, "s24": {"s3": ["s24:ingress7", "s24:egress6", "s8:ingress18", "s8:egress15", "s21:ingress6", "s21:egress7"]}}, "h151": {"s3": {"s15": ["s24:ingress7", "s24:egress1", "s3:ingress18", "s3:egress3", "s9:ingress1", "s9:egress6", "s8:ingress3", "s8:egress9", "s15:ingress6", "s15:egress7"]}, "s24": {"s3": ["s24:ingress7", "s24:egress6", "s8:ingress18", "s8:egress9", "s15:ingress6", "s15:egress7"]}}}, "h231": {"h241": {"s3": {"s24": ["s23:ingress7", "s23:egress1", "s3:ingress17", "s3:egress3", "s9:ingress1", "s9:egress6", "s8:ingress3", "s8:egress18", "s24:ingress6", "s24:egress7"]}, "s23": {"s3": ["s23:ingress7", "s23:egress6", "s8:ingress17", "s8:egress18", "s24:ingress6", "s24:egress7"]}}, "h171": {"s3": {"s17": ["s23:ingress7", "s23:egress1", "s3:ingress17", "s3:egress3", "s9:ingress1", "s9:egress6", "s8:ingress3", "s8:egress11", "s17:ingress6", "s17:egress7"]}, "s23": {"s3": ["s23:ingress7", "s23:egress6", "s8:ingress17", "s8:egress11", "s17:ingress6", "s17:egress7"]}}, "h111": {"s3": {"s11": ["s23:ingress7", "s23:egress1", "s3:ingress17", "s3:egress3", "s9:ingress1", "s9:egress6", "s8:ingress3", "s8:egress5", "s11:ingress6", "s11:egress7"]}, "s23": {"s3": ["s23:ingress7", "s23:egress6", "s8:ingress17", "s8:egress5", "s11:ingress6", "s11:egress7"]}}, "h131": {"s3": {"s13": ["s23:ingress7", "s23:egress1", "s3:ingress17", "s3:egress3", "s9:ingress1", "s9:egress6", "s8:ingress3", "s8:egress7", "s13:ingress6", "s13:egress7"]}, "s23": {"s3": ["s23:ingress7", "s23:egress6", "s8:ingress17", "s8:egress7", "s13:ingress6", "s13:egress7"]}}, "h121": {"s3": {"s12": ["s23:ingress7", "s23:egress1", "s3:ingress17", "s3:egress3", "s9:ingress1", "s9:egress6", "s8:ingress3", "s8:egress6", "s12:ingress6", "s12:egress7"]}, "s23": {"s3": ["s23:ingress7", "s23:egress6", "s8:ingress17", "s8:egress6", "s12:ingress6", "s12:egress7"]}}, "h261": {"s3": {"s26": ["s23:ingress7", "s23:egress1", "s3:ingress17", "s3:egress3", "s9:ingress1", "s9:egress6", "s8:ingress3", "s8:egress20", "s26:ingress6", "s26:egress7"]}, "s23": {"s3": ["s23:ingress7", "s23:egress6", "s8:ingress17", "s8:egress20", "s26:ingress6", "s26:egress7"]}}, "h91": {"s3": {"s9": ["s23:ingress7", "s23:egress1", "s3:ingress17", "s3:egress12", "s18:ingress1", "s18:egress6", "s8:ingress12", "s8:egress3", "s9:ingress6", "s9:egress7"]}, "s23": {"s3": ["s23:ingress7", "s23:egress6", "s8:ingress17", "s8:egress3", "s9:ingress6", "s9:egress7"]}}, "h161": {"s3": {"s16": ["s23:ingress7", "s23:egress1", "s3:ingress17", "s3:egress3", "s9:ingress1", "s9:egress6", "s8:ingress3", "s8:egress10", "s16:ingress6", "s16:egress7"]}, "s23": {"s3": ["s23:ingress7", "s23:egress6", "s8:ingress17", "s8:egress10", "s16:ingress6", "s16:egress7"]}}, "h191": {"s3": {"s19": ["s23:ingress7", "s23:egress1", "s3:ingress17", "s3:egress3", "s9:ingress1", "s9:egress6", "s8:ingress3", "s8:egress13", "s19:ingress6", "s19:egress7"]}, "s23": {"s3": ["s23:ingress7", "s23:egress6", "s8:ingress17", "s8:egress13", "s19:ingress6", "s19:egress7"]}}, "h101": {"s3": {"s10": ["s23:ingress7", "s23:egress1", "s3:ingress17", "s3:egress3", "s9:ingress1", "s9:egress6", "s8:ingress3", "s8:egress4", "s10:ingress6", "s10:egress7"]}, "s23": {"s3": ["s23:ingress7", "s23:egress6", "s8:ingress17", "s8:egress4", "s10:ingress6", "s10:egress7"]}}, "h221": {"s3": {"s22": ["s23:ingress7", "s23:egress1", "s3:ingress17", "s3:egress3", "s9:ingress1", "s9:egress6", "s8:ingress3", "s8:egress16", "s22:ingress6", "s22:egress7"]}, "s23": {"s3": ["s23:ingress7", "s23:egress6", "s8:ingress17", "s8:egress16", "s22:ingress6", "s22:egress7"]}}, "h141": {"s3": {"s14": ["s23:ingress7", "s23:egress1", "s3:ingress17", "s3:egress3", "s9:ingress1", "s9:egress6", "s8:ingress3", "s8:egress8", "s14:ingress6", "s14:egress7"]}, "s23": {"s3": ["s23:ingress7", "s23:egress6", "s8:ingress17", "s8:egress8", "s14:ingress6", "s14:egress7"]}}, "h251": {"s3": {"s25": ["s23:ingress7", "s23:egress1", "s3:ingress17", "s3:egress3", "s9:ingress1", "s9:egress6", "s8:ingress3", "s8:egress19", "s25:ingress6", "s25:egress7"]}, "s23": {"s3": ["s23:ingress7", "s23:egress6", "s8:ingress17", "s8:egress19", "s25:ingress6", "s25:egress7"]}}, "h201": {"s3": {"s20": ["s23:ingress7", "s23:egress1", "s3:ingress17", "s3:egress3", "s9:ingress1", "s9:egress6", "s8:ingress3", "s8:egress14", "s20:ingress6", "s20:egress7"]}, "s23": {"s3": ["s23:ingress7", "s23:egress6", "s8:ingress17", "s8:egress14", "s20:ingress6", "s20:egress7"]}}, "h181": {"s3": {"s18": ["s23:ingress7", "s23:egress1", "s3:ingress17", "s3:egress3", "s9:ingress1", "s9:egress6", "s8:ingress3", "s8:egress12", "s18:ingress6", "s18:egress7"]}, "s23": {"s3": ["s23:ingress7", "s23:egress6", "s8:ingress17", "s8:egress12", "s18:ingress6", "s18:egress7"]}}, "h211": {"s3": {"s21": ["s23:ingress7", "s23:egress1", "s3:ingress17", "s3:egress3", "s9:ingress1", "s9:egress6", "s8:ingress3", "s8:egress15", "s21:ingress6", "s21:egress7"]}, "s23": {"s3": ["s23:ingress7", "s23:egress6", "s8:ingress17", "s8:egress15", "s21:ingress6", "s21:egress7"]}}, "h151": {"s3": {"s15": ["s23:ingress7", "s23:egress1", "s3:ingress17", "s3:egress3", "s9:ingress1", "s9:egress6", "s8:ingress3", "s8:egress9", "s15:ingress6", "s15:egress7"]}, "s23": {"s3": ["s23:ingress7", "s23:egress6", "s8:ingress17", "s8:egress9", "s15:ingress6", "s15:egress7"]}}}, "h171": {"h241": {"s3": {"s24": ["s17:ingress7", "s17:egress1", "s3:ingress11", "s3:egress3", "s9:ingress1", "s9:egress6", "s8:ingress3", "s8:egress18", "s24:ingress6", "s24:egress7"]}, "s17": {"s3": ["s17:ingress7", "s17:egress6", "s8:ingress11", "s8:egress18", "s24:ingress6", "s24:egress7"]}}, "h231": {"s3": {"s23": ["s17:ingress7", "s17:egress1", "s3:ingress11", "s3:egress3", "s9:ingress1", "s9:egress6", "s8:ingress3", "s8:egress17", "s23:ingress6", "s23:egress7"]}, "s17": {"s3": ["s17:ingress7", "s17:egress6", "s8:ingress11", "s8:egress17", "s23:ingress6", "s23:egress7"]}}, "h221": {"s3": {"s22": ["s17:ingress7", "s17:egress1", "s3:ingress11", "s3:egress3", "s9:ingress1", "s9:egress6", "s8:ingress3", "s8:egress16", "s22:ingress6", "s22:egress7"]}, "s17": {"s3": ["s17:ingress7", "s17:egress6", "s8:ingress11", "s8:egress16", "s22:ingress6", "s22:egress7"]}}, "h111": {"s3": {"s11": ["s17:ingress7", "s17:egress1", "s3:ingress11", "s3:egress3", "s9:ingress1", "s9:egress6", "s8:ingress3", "s8:egress5", "s11:ingress6", "s11:egress7"]}, "s17": {"s3": ["s17:ingress7", "s17:egress6", "s8:ingress11", "s8:egress5", "s11:ingress6", "s11:egress7"]}}, "h131": {"s3": {"s13": ["s17:ingress7", "s17:egress1", "s3:ingress11", "s3:egress3", "s9:ingress1", "s9:egress6", "s8:ingress3", "s8:egress7", "s13:ingress6", "s13:egress7"]}, "s17": {"s3": ["s17:ingress7", "s17:egress6", "s8:ingress11", "s8:egress7", "s13:ingress6", "s13:egress7"]}}, "h121": {"s3": {"s12": ["s17:ingress7", "s17:egress1", "s3:ingress11", "s3:egress3", "s9:ingress1", "s9:egress6", "s8:ingress3", "s8:egress6", "s12:ingress6", "s12:egress7"]}, "s17": {"s3": ["s17:ingress7", "s17:egress6", "s8:ingress11", "s8:egress6", "s12:ingress6", "s12:egress7"]}}, "h261": {"s3": {"s26": ["s17:ingress7", "s17:egress1", "s3:ingress11", "s3:egress3", "s9:ingress1", "s9:egress6", "s8:ingress3", "s8:egress20", "s26:ingress6", "s26:egress7"]}, "s17": {"s3": ["s17:ingress7", "s17:egress6", "s8:ingress11", "s8:egress20", "s26:ingress6", "s26:egress7"]}}, "h91": {"s3": {"s9": ["s17:ingress7", "s17:egress1", "s3:ingress11", "s3:egress12", "s18:ingress1", "s18:egress6", "s8:ingress12", "s8:egress3", "s9:ingress6", "s9:egress7"]}, "s17": {"s3": ["s17:ingress7", "s17:egress6", "s8:ingress11", "s8:egress3", "s9:ingress6", "s9:egress7"]}}, "h161": {"s3": {"s16": ["s17:ingress7", "s17:egress1", "s3:ingress11", "s3:egress3", "s9:ingress1", "s9:egress6", "s8:ingress3", "s8:egress10", "s16:ingress6", "s16:egress7"]}, "s17": {"s3": ["s17:ingress7", "s17:egress6", "s8:ingress11", "s8:egress10", "s16:ingress6", "s16:egress7"]}}, "h191": {"s3": {"s19": ["s17:ingress7", "s17:egress1", "s3:ingress11", "s3:egress3", "s9:ingress1", "s9:egress6", "s8:ingress3", "s8:egress13", "s19:ingress6", "s19:egress7"]}, "s17": {"s3": ["s17:ingress7", "s17:egress6", "s8:ingress11", "s8:egress13", "s19:ingress6", "s19:egress7"]}}, "h101": {"s3": {"s10": ["s17:ingress7", "s17:egress1", "s3:ingress11", "s3:egress3", "s9:ingress1", "s9:egress6", "s8:ingress3", "s8:egress4", "s10:ingress6", "s10:egress7"]}, "s17": {"s3": ["s17:ingress7", "s17:egress6", "s8:ingress11", "s8:egress4", "s10:ingress6", "s10:egress7"]}}, "h141": {"s3": {"s14": ["s17:ingress7", "s17:egress1", "s3:ingress11", "s3:egress3", "s9:ingress1", "s9:egress6", "s8:ingress3", "s8:egress8", "s14:ingress6", "s14:egress7"]}, "s17": {"s3": ["s17:ingress7", "s17:egress6", "s8:ingress11", "s8:egress8", "s14:ingress6", "s14:egress7"]}}, "h251": {"s3": {"s25": ["s17:ingress7", "s17:egress1", "s3:ingress11", "s3:egress3", "s9:ingress1", "s9:egress6", "s8:ingress3", "s8:egress19", "s25:ingress6", "s25:egress7"]}, "s17": {"s3": ["s17:ingress7", "s17:egress6", "s8:ingress11", "s8:egress19", "s25:ingress6", "s25:egress7"]}}, "h201": {"s3": {"s20": ["s17:ingress7", "s17:egress1", "s3:ingress11", "s3:egress3", "s9:ingress1", "s9:egress6", "s8:ingress3", "s8:egress14", "s20:ingress6", "s20:egress7"]}, "s17": {"s3": ["s17:ingress7", "s17:egress6", "s8:ingress11", "s8:egress14", "s20:ingress6", "s20:egress7"]}}, "h181": {"s3": {"s18": ["s17:ingress7", "s17:egress1", "s3:ingress11", "s3:egress3", "s9:ingress1", "s9:egress6", "s8:ingress3", "s8:egress12", "s18:ingress6", "s18:egress7"]}, "s17": {"s3": ["s17:ingress7", "s17:egress6", "s8:ingress11", "s8:egress12", "s18:ingress6", "s18:egress7"]}}, "h211": {"s3": {"s21": ["s17:ingress7", "s17:egress1", "s3:ingress11", "s3:egress3", "s9:ingress1", "s9:egress6", "s8:ingress3", "s8:egress15", "s21:ingress6", "s21:egress7"]}, "s17": {"s3": ["s17:ingress7", "s17:egress6", "s8:ingress11", "s8:egress15", "s21:ingress6", "s21:egress7"]}}, "h151": {"s3": {"s15": ["s17:ingress7", "s17:egress1", "s3:ingress11", "s3:egress3", "s9:ingress1", "s9:egress6", "s8:ingress3", "s8:egress9", "s15:ingress6", "s15:egress7"]}, "s17": {"s3": ["s17:ingress7", "s17:egress6", "s8:ingress11", "s8:egress9", "s15:ingress6", "s15:egress7"]}}}, "h111": {"h231": {"s3": {"s23": ["s11:ingress7", "s11:egress1", "s3:ingress5", "s3:egress3", "s9:ingress1", "s9:egress6", "s8:ingress3", "s8:egress17", "s23:ingress6", "s23:egress7"]}, "s11": {"s3": ["s11:ingress7", "s11:egress6", "s8:ingress5", "s8:egress17", "s23:ingress6", "s23:egress7"]}}, "h171": {"s3": {"s17": ["s11:ingress7", "s11:egress1", "s3:ingress5", "s3:egress3", "s9:ingress1", "s9:egress6", "s8:ingress3", "s8:egress11", "s17:ingress6", "s17:egress7"]}, "s11": {"s3": ["s11:ingress7", "s11:egress6", "s8:ingress5", "s8:egress11", "s17:ingress6", "s17:egress7"]}}, "h241": {"s3": {"s24": ["s11:ingress7", "s11:egress1", "s3:ingress5", "s3:egress3", "s9:ingress1", "s9:egress6", "s8:ingress3", "s8:egress18", "s24:ingress6", "s24:egress7"]}, "s11": {"s3": ["s11:ingress7", "s11:egress6", "s8:ingress5", "s8:egress18", "s24:ingress6", "s24:egress7"]}}, "h131": {"s3": {"s13": ["s11:ingress7", "s11:egress1", "s3:ingress5", "s3:egress3", "s9:ingress1", "s9:egress6", "s8:ingress3", "s8:egress7", "s13:ingress6", "s13:egress7"]}, "s11": {"s3": ["s11:ingress7", "s11:egress6", "s8:ingress5", "s8:egress7", "s13:ingress6", "s13:egress7"]}}, "h121": {"s3": {"s12": ["s11:ingress7", "s11:egress1", "s3:ingress5", "s3:egress3", "s9:ingress1", "s9:egress6", "s8:ingress3", "s8:egress6", "s12:ingress6", "s12:egress7"]}, "s11": {"s3": ["s11:ingress7", "s11:egress6", "s8:ingress5", "s8:egress6", "s12:ingress6", "s12:egress7"]}}, "h261": {"s3": {"s26": ["s11:ingress7", "s11:egress1", "s3:ingress5", "s3:egress3", "s9:ingress1", "s9:egress6", "s8:ingress3", "s8:egress20", "s26:ingress6", "s26:egress7"]}, "s11": {"s3": ["s11:ingress7", "s11:egress6", "s8:ingress5", "s8:egress20", "s26:ingress6", "s26:egress7"]}}, "h91": {"s3": {"s9": ["s11:ingress7", "s11:egress1", "s3:ingress5", "s3:egress12", "s18:ingress1", "s18:egress6", "s8:ingress12", "s8:egress3", "s9:ingress6", "s9:egress7"]}, "s11": {"s3": ["s11:ingress7", "s11:egress6", "s8:ingress5", "s8:egress3", "s9:ingress6", "s9:egress7"]}}, "h161": {"s3": {"s16": ["s11:ingress7", "s11:egress1", "s3:ingress5", "s3:egress3", "s9:ingress1", "s9:egress6", "s8:ingress3", "s8:egress10", "s16:ingress6", "s16:egress7"]}, "s11": {"s3": ["s11:ingress7", "s11:egress6", "s8:ingress5", "s8:egress10", "s16:ingress6", "s16:egress7"]}}, "h191": {"s3": {"s19": ["s11:ingress7", "s11:egress1", "s3:ingress5", "s3:egress3", "s9:ingress1", "s9:egress6", "s8:ingress3", "s8:egress13", "s19:ingress6", "s19:egress7"]}, "s11": {"s3": ["s11:ingress7", "s11:egress6", "s8:ingress5", "s8:egress13", "s19:ingress6", "s19:egress7"]}}, "h101": {"s3": {"s10": ["s11:ingress7", "s11:egress1", "s3:ingress5", "s3:egress3", "s9:ingress1", "s9:egress6", "s8:ingress3", "s8:egress4", "s10:ingress6", "s10:egress7"]}, "s11": {"s3": ["s11:ingress7", "s11:egress6", "s8:ingress5", "s8:egress4", "s10:ingress6", "s10:egress7"]}}, "h221": {"s3": {"s22": ["s11:ingress7", "s11:egress1", "s3:ingress5", "s3:egress3", "s9:ingress1", "s9:egress6", "s8:ingress3", "s8:egress16", "s22:ingress6", "s22:egress7"]}, "s11": {"s3": ["s11:ingress7", "s11:egress6", "s8:ingress5", "s8:egress16", "s22:ingress6", "s22:egress7"]}}, "h141": {"s3": {"s14": ["s11:ingress7", "s11:egress1", "s3:ingress5", "s3:egress3", "s9:ingress1", "s9:egress6", "s8:ingress3", "s8:egress8", "s14:ingress6", "s14:egress7"]}, "s11": {"s3": ["s11:ingress7", "s11:egress6", "s8:ingress5", "s8:egress8", "s14:ingress6", "s14:egress7"]}}, "h251": {"s3": {"s25": ["s11:ingress7", "s11:egress1", "s3:ingress5", "s3:egress3", "s9:ingress1", "s9:egress6", "s8:ingress3", "s8:egress19", "s25:ingress6", "s25:egress7"]}, "s11": {"s3": ["s11:ingress7", "s11:egress6", "s8:ingress5", "s8:egress19", "s25:ingress6", "s25:egress7"]}}, "h201": {"s3": {"s20": ["s11:ingress7", "s11:egress1", "s3:ingress5", "s3:egress3", "s9:ingress1", "s9:egress6", "s8:ingress3", "s8:egress14", "s20:ingress6", "s20:egress7"]}, "s11": {"s3": ["s11:ingress7", "s11:egress6", "s8:ingress5", "s8:egress14", "s20:ingress6", "s20:egress7"]}}, "h181": {"s3": {"s18": ["s11:ingress7", "s11:egress1", "s3:ingress5", "s3:egress3", "s9:ingress1", "s9:egress6", "s8:ingress3", "s8:egress12", "s18:ingress6", "s18:egress7"]}, "s11": {"s3": ["s11:ingress7", "s11:egress6", "s8:ingress5", "s8:egress12", "s18:ingress6", "s18:egress7"]}}, "h211": {"s3": {"s21": ["s11:ingress7", "s11:egress1", "s3:ingress5", "s3:egress3", "s9:ingress1", "s9:egress6", "s8:ingress3", "s8:egress15", "s21:ingress6", "s21:egress7"]}, "s11": {"s3": ["s11:ingress7", "s11:egress6", "s8:ingress5", "s8:egress15", "s21:ingress6", "s21:egress7"]}}, "h151": {"s3": {"s15": ["s11:ingress7", "s11:egress1", "s3:ingress5", "s3:egress3", "s9:ingress1", "s9:egress6", "s8:ingress3", "s8:egress9", "s15:ingress6", "s15:egress7"]}, "s11": {"s3": ["s11:ingress7", "s11:egress6", "s8:ingress5", "s8:egress9", "s15:ingress6", "s15:egress7"]}}}, "h131": {"h241": {"s13": {"s3": ["s13:ingress7", "s13:egress6", "s8:ingress7", "s8:egress18", "s24:ingress6", "s24:egress7"]}, "s3": {"s24": ["s13:ingress7", "s13:egress1", "s3:ingress7", "s3:egress3", "s9:ingress1", "s9:egress6", "s8:ingress3", "s8:egress18", "s24:ingress6", "s24:egress7"]}}, "h171": {"s13": {"s3": ["s13:ingress7", "s13:egress6", "s8:ingress7", "s8:egress11", "s17:ingress6", "s17:egress7"]}, "s3": {"s17": ["s13:ingress7", "s13:egress1", "s3:ingress7", "s3:egress3", "s9:ingress1", "s9:egress6", "s8:ingress3", "s8:egress11", "s17:ingress6", "s17:egress7"]}}, "h111": {"s13": {"s3": ["s13:ingress7", "s13:egress6", "s8:ingress7", "s8:egress5", "s11:ingress6", "s11:egress7"]}, "s3": {"s11": ["s13:ingress7", "s13:egress1", "s3:ingress7", "s3:egress3", "s9:ingress1", "s9:egress6", "s8:ingress3", "s8:egress5", "s11:ingress6", "s11:egress7"]}}, "h231": {"s13": {"s3": ["s13:ingress7", "s13:egress6", "s8:ingress7", "s8:egress17", "s23:ingress6", "s23:egress7"]}, "s3": {"s23": ["s13:ingress7", "s13:egress1", "s3:ingress7", "s3:egress3", "s9:ingress1", "s9:egress6", "s8:ingress3", "s8:egress17", "s23:ingress6", "s23:egress7"]}}, "h121": {"s13": {"s3": ["s13:ingress7", "s13:egress6", "s8:ingress7", "s8:egress6", "s12:ingress6", "s12:egress7"]}, "s3": {"s12": ["s13:ingress7", "s13:egress1", "s3:ingress7", "s3:egress3", "s9:ingress1", "s9:egress6", "s8:ingress3", "s8:egress6", "s12:ingress6", "s12:egress7"]}}, "h261": {"s13": {"s3": ["s13:ingress7", "s13:egress6", "s8:ingress7", "s8:egress20", "s26:ingress6", "s26:egress7"]}, "s3": {"s26": ["s13:ingress7", "s13:egress1", "s3:ingress7", "s3:egress3", "s9:ingress1", "s9:egress6", "s8:ingress3", "s8:egress20", "s26:ingress6", "s26:egress7"]}}, "h91": {"s13": {"s3": ["s13:ingress7", "s13:egress6", "s8:ingress7", "s8:egress3", "s9:ingress6", "s9:egress7"]}, "s3": {"s9": ["s13:ingress7", "s13:egress1", "s3:ingress7", "s3:egress12", "s18:ingress1", "s18:egress6", "s8:ingress12", "s8:egress3", "s9:ingress6", "s9:egress7"]}}, "h161": {"s13": {"s3": ["s13:ingress7", "s13:egress6", "s8:ingress7", "s8:egress10", "s16:ingress6", "s16:egress7"]}, "s3": {"s16": ["s13:ingress7", "s13:egress1", "s3:ingress7", "s3:egress3", "s9:ingress1", "s9:egress6", "s8:ingress3", "s8:egress10", "s16:ingress6", "s16:egress7"]}}, "h191": {"s13": {"s3": ["s13:ingress7", "s13:egress6", "s8:ingress7", "s8:egress13", "s19:ingress6", "s19:egress7"]}, "s3": {"s19": ["s13:ingress7", "s13:egress1", "s3:ingress7", "s3:egress3", "s9:ingress1", "s9:egress6", "s8:ingress3", "s8:egress13", "s19:ingress6", "s19:egress7"]}}, "h101": {"s13": {"s3": ["s13:ingress7", "s13:egress6", "s8:ingress7", "s8:egress4", "s10:ingress6", "s10:egress7"]}, "s3": {"s10": ["s13:ingress7", "s13:egress1", "s3:ingress7", "s3:egress3", "s9:ingress1", "s9:egress6", "s8:ingress3", "s8:egress4", "s10:ingress6", "s10:egress7"]}}, "h221": {"s13": {"s3": ["s13:ingress7", "s13:egress6", "s8:ingress7", "s8:egress16", "s22:ingress6", "s22:egress7"]}, "s3": {"s22": ["s13:ingress7", "s13:egress1", "s3:ingress7", "s3:egress3", "s9:ingress1", "s9:egress6", "s8:ingress3", "s8:egress16", "s22:ingress6", "s22:egress7"]}}, "h141": {"s13": {"s3": ["s13:ingress7", "s13:egress6", "s8:ingress7", "s8:egress8", "s14:ingress6", "s14:egress7"]}, "s3": {"s14": ["s13:ingress7", "s13:egress1", "s3:ingress7", "s3:egress3", "s9:ingress1", "s9:egress6", "s8:ingress3", "s8:egress8", "s14:ingress6", "s14:egress7"]}}, "h251": {"s13": {"s3": ["s13:ingress7", "s13:egress6", "s8:ingress7", "s8:egress19", "s25:ingress6", "s25:egress7"]}, "s3": {"s25": ["s13:ingress7", "s13:egress1", "s3:ingress7", "s3:egress3", "s9:ingress1", "s9:egress6", "s8:ingress3", "s8:egress19", "s25:ingress6", "s25:egress7"]}}, "h201": {"s13": {"s3": ["s13:ingress7", "s13:egress6", "s8:ingress7", "s8:egress14", "s20:ingress6", "s20:egress7"]}, "s3": {"s20": ["s13:ingress7", "s13:egress1", "s3:ingress7", "s3:egress3", "s9:ingress1", "s9:egress6", "s8:ingress3", "s8:egress14", "s20:ingress6", "s20:egress7"]}}, "h181": {"s13": {"s3": ["s13:ingress7", "s13:egress6", "s8:ingress7", "s8:egress12", "s18:ingress6", "s18:egress7"]}, "s3": {"s18": ["s13:ingress7", "s13:egress1", "s3:ingress7", "s3:egress3", "s9:ingress1", "s9:egress6", "s8:ingress3", "s8:egress12", "s18:ingress6", "s18:egress7"]}}, "h211": {"s13": {"s3": ["s13:ingress7", "s13:egress6", "s8:ingress7", "s8:egress15", "s21:ingress6", "s21:egress7"]}, "s3": {"s21": ["s13:ingress7", "s13:egress1", "s3:ingress7", "s3:egress3", "s9:ingress1", "s9:egress6", "s8:ingress3", "s8:egress15", "s21:ingress6", "s21:egress7"]}}, "h151": {"s13": {"s3": ["s13:ingress7", "s13:egress6", "s8:ingress7", "s8:egress9", "s15:ingress6", "s15:egress7"]}, "s3": {"s15": ["s13:ingress7", "s13:egress1", "s3:ingress7", "s3:egress3", "s9:ingress1", "s9:egress6", "s8:ingress3", "s8:egress9", "s15:ingress6", "s15:egress7"]}}}, "h121": {"h241": {"s3": {"s24": ["s12:ingress7", "s12:egress1", "s3:ingress6", "s3:egress3", "s9:ingress1", "s9:egress6", "s8:ingress3", "s8:egress18", "s24:ingress6", "s24:egress7"]}, "s12": {"s3": ["s12:ingress7", "s12:egress6", "s8:ingress6", "s8:egress18", "s24:ingress6", "s24:egress7"]}}, "h231": {"s3": {"s23": ["s12:ingress7", "s12:egress1", "s3:ingress6", "s3:egress3", "s9:ingress1", "s9:egress6", "s8:ingress3", "s8:egress17", "s23:ingress6", "s23:egress7"]}, "s12": {"s3": ["s12:ingress7", "s12:egress6", "s8:ingress6", "s8:egress17", "s23:ingress6", "s23:egress7"]}}, "h171": {"s3": {"s17": ["s12:ingress7", "s12:egress1", "s3:ingress6", "s3:egress3", "s9:ingress1", "s9:egress6", "s8:ingress3", "s8:egress11", "s17:ingress6", "s17:egress7"]}, "s12": {"s3": ["s12:ingress7", "s12:egress6", "s8:ingress6", "s8:egress11", "s17:ingress6", "s17:egress7"]}}, "h111": {"s3": {"s11": ["s12:ingress7", "s12:egress1", "s3:ingress6", "s3:egress3", "s9:ingress1", "s9:egress6", "s8:ingress3", "s8:egress5", "s11:ingress6", "s11:egress7"]}, "s12": {"s3": ["s12:ingress7", "s12:egress6", "s8:ingress6", "s8:egress5", "s11:ingress6", "s11:egress7"]}}, "h131": {"s3": {"s13": ["s12:ingress7", "s12:egress1", "s3:ingress6", "s3:egress3", "s9:ingress1", "s9:egress6", "s8:ingress3", "s8:egress7", "s13:ingress6", "s13:egress7"]}, "s12": {"s3": ["s12:ingress7", "s12:egress6", "s8:ingress6", "s8:egress7", "s13:ingress6", "s13:egress7"]}}, "h261": {"s3": {"s26": ["s12:ingress7", "s12:egress1", "s3:ingress6", "s3:egress3", "s9:ingress1", "s9:egress6", "s8:ingress3", "s8:egress20", "s26:ingress6", "s26:egress7"]}, "s12": {"s3": ["s12:ingress7", "s12:egress6", "s8:ingress6", "s8:egress20", "s26:ingress6", "s26:egress7"]}}, "h91": {"s3": {"s9": ["s12:ingress7", "s12:egress1", "s3:ingress6", "s3:egress12", "s18:ingress1", "s18:egress6", "s8:ingress12", "s8:egress3", "s9:ingress6", "s9:egress7"]}, "s12": {"s3": ["s12:ingress7", "s12:egress6", "s8:ingress6", "s8:egress3", "s9:ingress6", "s9:egress7"]}}, "h161": {"s3": {"s16": ["s12:ingress7", "s12:egress1", "s3:ingress6", "s3:egress3", "s9:ingress1", "s9:egress6", "s8:ingress3", "s8:egress10", "s16:ingress6", "s16:egress7"]}, "s12": {"s3": ["s12:ingress7", "s12:egress6", "s8:ingress6", "s8:egress10", "s16:ingress6", "s16:egress7"]}}, "h191": {"s3": {"s19": ["s12:ingress7", "s12:egress1", "s3:ingress6", "s3:egress3", "s9:ingress1", "s9:egress6", "s8:ingress3", "s8:egress13", "s19:ingress6", "s19:egress7"]}, "s12": {"s3": ["s12:ingress7", "s12:egress6", "s8:ingress6", "s8:egress13", "s19:ingress6", "s19:egress7"]}}, "h101": {"s3": {"s10": ["s12:ingress7", "s12:egress1", "s3:ingress6", "s3:egress3", "s9:ingress1", "s9:egress6", "s8:ingress3", "s8:egress4", "s10:ingress6", "s10:egress7"]}, "s12": {"s3": ["s12:ingress7", "s12:egress6", "s8:ingress6", "s8:egress4", "s10:ingress6", "s10:egress7"]}}, "h221": {"s3": {"s22": ["s12:ingress7", "s12:egress1", "s3:ingress6", "s3:egress3", "s9:ingress1", "s9:egress6", "s8:ingress3", "s8:egress16", "s22:ingress6", "s22:egress7"]}, "s12": {"s3": ["s12:ingress7", "s12:egress6", "s8:ingress6", "s8:egress16", "s22:ingress6", "s22:egress7"]}}, "h141": {"s3": {"s14": ["s12:ingress7", "s12:egress1", "s3:ingress6", "s3:egress3", "s9:ingress1", "s9:egress6", "s8:ingress3", "s8:egress8", "s14:ingress6", "s14:egress7"]}, "s12": {"s3": ["s12:ingress7", "s12:egress6", "s8:ingress6", "s8:egress8", "s14:ingress6", "s14:egress7"]}}, "h251": {"s3": {"s25": ["s12:ingress7", "s12:egress1", "s3:ingress6", "s3:egress3", "s9:ingress1", "s9:egress6", "s8:ingress3", "s8:egress19", "s25:ingress6", "s25:egress7"]}, "s12": {"s3": ["s12:ingress7", "s12:egress6", "s8:ingress6", "s8:egress19", "s25:ingress6", "s25:egress7"]}}, "h201": {"s3": {"s20": ["s12:ingress7", "s12:egress1", "s3:ingress6", "s3:egress3", "s9:ingress1", "s9:egress6", "s8:ingress3", "s8:egress14", "s20:ingress6", "s20:egress7"]}, "s12": {"s3": ["s12:ingress7", "s12:egress6", "s8:ingress6", "s8:egress14", "s20:ingress6", "s20:egress7"]}}, "h181": {"s3": {"s18": ["s12:ingress7", "s12:egress1", "s3:ingress6", "s3:egress3", "s9:ingress1", "s9:egress6", "s8:ingress3", "s8:egress12", "s18:ingress6", "s18:egress7"]}, "s12": {"s3": ["s12:ingress7", "s12:egress6", "s8:ingress6", "s8:egress12", "s18:ingress6", "s18:egress7"]}}, "h211": {"s3": {"s21": ["s12:ingress7", "s12:egress1", "s3:ingress6", "s3:egress3", "s9:ingress1", "s9:egress6", "s8:ingress3", "s8:egress15", "s21:ingress6", "s21:egress7"]}, "s12": {"s3": ["s12:ingress7", "s12:egress6", "s8:ingress6", "s8:egress15", "s21:ingress6", "s21:egress7"]}}, "h151": {"s3": {"s15": ["s12:ingress7", "s12:egress1", "s3:ingress6", "s3:egress3", "s9:ingress1", "s9:egress6", "s8:ingress3", "s8:egress9", "s15:ingress6", "s15:egress7"]}, "s12": {"s3": ["s12:ingress7", "s12:egress6", "s8:ingress6", "s8:egress9", "s15:ingress6", "s15:egress7"]}}}, "h261": {"h241": {"s3": {"s24": ["s26:ingress7", "s26:egress1", "s3:ingress20", "s3:egress3", "s9:ingress1", "s9:egress6", "s8:ingress3", "s8:egress18", "s24:ingress6", "s24:egress7"]}, "s26": {"s3": ["s26:ingress7", "s26:egress6", "s8:ingress20", "s8:egress18", "s24:ingress6", "s24:egress7"]}}, "h231": {"s3": {"s23": ["s26:ingress7", "s26:egress1", "s3:ingress20", "s3:egress3", "s9:ingress1", "s9:egress6", "s8:ingress3", "s8:egress17", "s23:ingress6", "s23:egress7"]}, "s26": {"s3": ["s26:ingress7", "s26:egress6", "s8:ingress20", "s8:egress17", "s23:ingress6", "s23:egress7"]}}, "h171": {"s3": {"s17": ["s26:ingress7", "s26:egress1", "s3:ingress20", "s3:egress3", "s9:ingress1", "s9:egress6", "s8:ingress3", "s8:egress11", "s17:ingress6", "s17:egress7"]}, "s26": {"s3": ["s26:ingress7", "s26:egress6", "s8:ingress20", "s8:egress11", "s17:ingress6", "s17:egress7"]}}, "h111": {"s3": {"s11": ["s26:ingress7", "s26:egress1", "s3:ingress20", "s3:egress3", "s9:ingress1", "s9:egress6", "s8:ingress3", "s8:egress5", "s11:ingress6", "s11:egress7"]}, "s26": {"s3": ["s26:ingress7", "s26:egress6", "s8:ingress20", "s8:egress5", "s11:ingress6", "s11:egress7"]}}, "h131": {"s3": {"s13": ["s26:ingress7", "s26:egress1", "s3:ingress20", "s3:egress3", "s9:ingress1", "s9:egress6", "s8:ingress3", "s8:egress7", "s13:ingress6", "s13:egress7"]}, "s26": {"s3": ["s26:ingress7", "s26:egress6", "s8:ingress20", "s8:egress7", "s13:ingress6", "s13:egress7"]}}, "h121": {"s3": {"s12": ["s26:ingress7", "s26:egress1", "s3:ingress20", "s3:egress3", "s9:ingress1", "s9:egress6", "s8:ingress3", "s8:egress6", "s12:ingress6", "s12:egress7"]}, "s26": {"s3": ["s26:ingress7", "s26:egress6", "s8:ingress20", "s8:egress6", "s12:ingress6", "s12:egress7"]}}, "h91": {"s3": {"s9": ["s26:ingress7", "s26:egress1", "s3:ingress20", "s3:egress12", "s18:ingress1", "s18:egress6", "s8:ingress12", "s8:egress3", "s9:ingress6", "s9:egress7"]}, "s26": {"s3": ["s26:ingress7", "s26:egress6", "s8:ingress20", "s8:egress3", "s9:ingress6", "s9:egress7"]}}, "h161": {"s3": {"s16": ["s26:ingress7", "s26:egress1", "s3:ingress20", "s3:egress3", "s9:ingress1", "s9:egress6", "s8:ingress3", "s8:egress10", "s16:ingress6", "s16:egress7"]}, "s26": {"s3": ["s26:ingress7", "s26:egress6", "s8:ingress20", "s8:egress10", "s16:ingress6", "s16:egress7"]}}, "h191": {"s3": {"s19": ["s26:ingress7", "s26:egress1", "s3:ingress20", "s3:egress3", "s9:ingress1", "s9:egress6", "s8:ingress3", "s8:egress13", "s19:ingress6", "s19:egress7"]}, "s26": {"s3": ["s26:ingress7", "s26:egress6", "s8:ingress20", "s8:egress13", "s19:ingress6", "s19:egress7"]}}, "h101": {"s3": {"s10": ["s26:ingress7", "s26:egress1", "s3:ingress20", "s3:egress3", "s9:ingress1", "s9:egress6", "s8:ingress3", "s8:egress4", "s10:ingress6", "s10:egress7"]}, "s26": {"s3": ["s26:ingress7", "s26:egress6", "s8:ingress20", "s8:egress4", "s10:ingress6", "s10:egress7"]}}, "h221": {"s3": {"s22": ["s26:ingress7", "s26:egress1", "s3:ingress20", "s3:egress3", "s9:ingress1", "s9:egress6", "s8:ingress3", "s8:egress16", "s22:ingress6", "s22:egress7"]}, "s26": {"s3": ["s26:ingress7", "s26:egress6", "s8:ingress20", "s8:egress16", "s22:ingress6", "s22:egress7"]}}, "h141": {"s3": {"s14": ["s26:ingress7", "s26:egress1", "s3:ingress20", "s3:egress3", "s9:ingress1", "s9:egress6", "s8:ingress3", "s8:egress8", "s14:ingress6", "s14:egress7"]}, "s26": {"s3": ["s26:ingress7", "s26:egress6", "s8:ingress20", "s8:egress8", "s14:ingress6", "s14:egress7"]}}, "h251": {"s3": {"s25": ["s26:ingress7", "s26:egress1", "s3:ingress20", "s3:egress3", "s9:ingress1", "s9:egress6", "s8:ingress3", "s8:egress19", "s25:ingress6", "s25:egress7"]}, "s26": {"s3": ["s26:ingress7", "s26:egress6", "s8:ingress20", "s8:egress19", "s25:ingress6", "s25:egress7"]}}, "h201": {"s3": {"s20": ["s26:ingress7", "s26:egress1", "s3:ingress20", "s3:egress3", "s9:ingress1", "s9:egress6", "s8:ingress3", "s8:egress14", "s20:ingress6", "s20:egress7"]}, "s26": {"s3": ["s26:ingress7", "s26:egress6", "s8:ingress20", "s8:egress14", "s20:ingress6", "s20:egress7"]}}, "h181": {"s3": {"s18": ["s26:ingress7", "s26:egress1", "s3:ingress20", "s3:egress3", "s9:ingress1", "s9:egress6", "s8:ingress3", "s8:egress12", "s18:ingress6", "s18:egress7"]}, "s26": {"s3": ["s26:ingress7", "s26:egress6", "s8:ingress20", "s8:egress12", "s18:ingress6", "s18:egress7"]}}, "h211": {"s3": {"s21": ["s26:ingress7", "s26:egress1", "s3:ingress20", "s3:egress3", "s9:ingress1", "s9:egress6", "s8:ingress3", "s8:egress15", "s21:ingress6", "s21:egress7"]}, "s26": {"s3": ["s26:ingress7", "s26:egress6", "s8:ingress20", "s8:egress15", "s21:ingress6", "s21:egress7"]}}, "h151": {"s3": {"s15": ["s26:ingress7", "s26:egress1", "s3:ingress20", "s3:egress3", "s9:ingress1", "s9:egress6", "s8:ingress3", "s8:egress9", "s15:ingress6", "s15:egress7"]}, "s26": {"s3": ["s26:ingress7", "s26:egress6", "s8:ingress20", "s8:egress9", "s15:ingress6", "s15:egress7"]}}}, "h91": {"h241": {"s3": {"s24": ["s9:ingress7", "s9:egress1", "s3:ingress3", "s3:egress3", "s9:ingress1", "s9:egress6", "s8:ingress3", "s8:egress18", "s24:ingress6", "s24:egress7"]}, "s9": {"s3": ["s9:ingress7", "s9:egress6", "s8:ingress3", "s8:egress18", "s24:ingress6", "s24:egress7"]}}, "h231": {"s3": {"s23": ["s9:ingress7", "s9:egress1", "s3:ingress3", "s3:egress3", "s9:ingress1", "s9:egress6", "s8:ingress3", "s8:egress17", "s23:ingress6", "s23:egress7"]}, "s9": {"s3": ["s9:ingress7", "s9:egress6", "s8:ingress3", "s8:egress17", "s23:ingress6", "s23:egress7"]}}, "h221": {"s3": {"s22": ["s9:ingress7", "s9:egress1", "s3:ingress3", "s3:egress3", "s9:ingress1", "s9:egress6", "s8:ingress3", "s8:egress16", "s22:ingress6", "s22:egress7"]}, "s9": {"s3": ["s9:ingress7", "s9:egress6", "s8:ingress3", "s8:egress16", "s22:ingress6", "s22:egress7"]}}, "h111": {"s3": {"s11": ["s9:ingress7", "s9:egress1", "s3:ingress3", "s3:egress3", "s9:ingress1", "s9:egress6", "s8:ingress3", "s8:egress5", "s11:ingress6", "s11:egress7"]}, "s9": {"s3": ["s9:ingress7", "s9:egress6", "s8:ingress3", "s8:egress5", "s11:ingress6", "s11:egress7"]}}, "h131": {"s3": {"s13": ["s9:ingress7", "s9:egress1", "s3:ingress3", "s3:egress3", "s9:ingress1", "s9:egress6", "s8:ingress3", "s8:egress7", "s13:ingress6", "s13:egress7"]}, "s9": {"s3": ["s9:ingress7", "s9:egress6", "s8:ingress3", "s8:egress7", "s13:ingress6", "s13:egress7"]}}, "h121": {"s3": {"s12": ["s9:ingress7", "s9:egress1", "s3:ingress3", "s3:egress3", "s9:ingress1", "s9:egress6", "s8:ingress3", "s8:egress6", "s12:ingress6", "s12:egress7"]}, "s9": {"s3": ["s9:ingress7", "s9:egress6", "s8:ingress3", "s8:egress6", "s12:ingress6", "s12:egress7"]}}, "h261": {"s3": {"s26": ["s9:ingress7", "s9:egress1", "s3:ingress3", "s3:egress3", "s9:ingress1", "s9:egress6", "s8:ingress3", "s8:egress20", "s26:ingress6", "s26:egress7"]}, "s9": {"s3": ["s9:ingress7", "s9:egress6", "s8:ingress3", "s8:egress20", "s26:ingress6", "s26:egress7"]}}, "h171": {"s3": {"s17": ["s9:ingress7", "s9:egress1", "s3:ingress3", "s3:egress3", "s9:ingress1", "s9:egress6", "s8:ingress3", "s8:egress11", "s17:ingress6", "s17:egress7"]}, "s9": {"s3": ["s9:ingress7", "s9:egress6", "s8:ingress3", "s8:egress11", "s17:ingress6", "s17:egress7"]}}, "h161": {"s3": {"s16": ["s9:ingress7", "s9:egress1", "s3:ingress3", "s3:egress3", "s9:ingress1", "s9:egress6", "s8:ingress3", "s8:egress10", "s16:ingress6", "s16:egress7"]}, "s9": {"s3": ["s9:ingress7", "s9:egress6", "s8:ingress3", "s8:egress10", "s16:ingress6", "s16:egress7"]}}, "h191": {"s3": {"s19": ["s9:ingress7", "s9:egress1", "s3:ingress3", "s3:egress3", "s9:ingress1", "s9:egress6", "s8:ingress3", "s8:egress13", "s19:ingress6", "s19:egress7"]}, "s9": {"s3": ["s9:ingress7", "s9:egress6", "s8:ingress3", "s8:egress13", "s19:ingress6", "s19:egress7"]}}, "h101": {"s3": {"s10": ["s9:ingress7", "s9:egress1", "s3:ingress3", "s3:egress3", "s9:ingress1", "s9:egress6", "s8:ingress3", "s8:egress4", "s10:ingress6", "s10:egress7"]}, "s9": {"s3": ["s9:ingress7", "s9:egress6", "s8:ingress3", "s8:egress4", "s10:ingress6", "s10:egress7"]}}, "h141": {"s3": {"s14": ["s9:ingress7", "s9:egress1", "s3:ingress3", "s3:egress3", "s9:ingress1", "s9:egress6", "s8:ingress3", "s8:egress8", "s14:ingress6", "s14:egress7"]}, "s9": {"s3": ["s9:ingress7", "s9:egress6", "s8:ingress3", "s8:egress8", "s14:ingress6", "s14:egress7"]}}, "h251": {"s3": {"s25": ["s9:ingress7", "s9:egress1", "s3:ingress3", "s3:egress3", "s9:ingress1", "s9:egress6", "s8:ingress3", "s8:egress19", "s25:ingress6", "s25:egress7"]}, "s9": {"s3": ["s9:ingress7", "s9:egress6", "s8:ingress3", "s8:egress19", "s25:ingress6", "s25:egress7"]}}, "h201": {"s3": {"s20": ["s9:ingress7", "s9:egress1", "s3:ingress3", "s3:egress3", "s9:ingress1", "s9:egress6", "s8:ingress3", "s8:egress14", "s20:ingress6", "s20:egress7"]}, "s9": {"s3": ["s9:ingress7", "s9:egress6", "s8:ingress3", "s8:egress14", "s20:ingress6", "s20:egress7"]}}, "h181": {"s3": {"s18": ["s9:ingress7", "s9:egress1", "s3:ingress3", "s3:egress3", "s9:ingress1", "s9:egress6", "s8:ingress3", "s8:egress12", "s18:ingress6", "s18:egress7"]}, "s9": {"s3": ["s9:ingress7", "s9:egress6", "s8:ingress3", "s8:egress12", "s18:ingress6", "s18:egress7"]}}, "h211": {"s3": {"s21": ["s9:ingress7", "s9:egress1", "s3:ingress3", "s3:egress3", "s9:ingress1", "s9:egress6", "s8:ingress3", "s8:egress15", "s21:ingress6", "s21:egress7"]}, "s9": {"s3": ["s9:ingress7", "s9:egress6", "s8:ingress3", "s8:egress15", "s21:ingress6", "s21:egress7"]}}, "h151": {"s3": {"s15": ["s9:ingress7", "s9:egress1", "s3:ingress3", "s3:egress3", "s9:ingress1", "s9:egress6", "s8:ingress3", "s8:egress9", "s15:ingress6", "s15:egress7"]}, "s9": {"s3": ["s9:ingress7", "s9:egress6", "s8:ingress3", "s8:egress9", "s15:ingress6", "s15:egress7"]}}}, "h161": {"h241": {"s3": {"s24": ["s16:ingress7", "s16:egress1", "s3:ingress10", "s3:egress3", "s9:ingress1", "s9:egress6", "s8:ingress3", "s8:egress18", "s24:ingress6", "s24:egress7"]}, "s16": {"s3": ["s16:ingress7", "s16:egress6", "s8:ingress10", "s8:egress18", "s24:ingress6", "s24:egress7"]}}, "h171": {"s3": {"s17": ["s16:ingress7", "s16:egress1", "s3:ingress10", "s3:egress3", "s9:ingress1", "s9:egress6", "s8:ingress3", "s8:egress11", "s17:ingress6", "s17:egress7"]}, "s16": {"s3": ["s16:ingress7", "s16:egress6", "s8:ingress10", "s8:egress11", "s17:ingress6", "s17:egress7"]}}, "h111": {"s3": {"s11": ["s16:ingress7", "s16:egress1", "s3:ingress10", "s3:egress3", "s9:ingress1", "s9:egress6", "s8:ingress3", "s8:egress5", "s11:ingress6", "s11:egress7"]}, "s16": {"s3": ["s16:ingress7", "s16:egress6", "s8:ingress10", "s8:egress5", "s11:ingress6", "s11:egress7"]}}, "h131": {"s3": {"s13": ["s16:ingress7", "s16:egress1", "s3:ingress10", "s3:egress3", "s9:ingress1", "s9:egress6", "s8:ingress3", "s8:egress7", "s13:ingress6", "s13:egress7"]}, "s16": {"s3": ["s16:ingress7", "s16:egress6", "s8:ingress10", "s8:egress7", "s13:ingress6", "s13:egress7"]}}, "h121": {"s3": {"s12": ["s16:ingress7", "s16:egress1", "s3:ingress10", "s3:egress3", "s9:ingress1", "s9:egress6", "s8:ingress3", "s8:egress6", "s12:ingress6", "s12:egress7"]}, "s16": {"s3": ["s16:ingress7", "s16:egress6", "s8:ingress10", "s8:egress6", "s12:ingress6", "s12:egress7"]}}, "h261": {"s3": {"s26": ["s16:ingress7", "s16:egress1", "s3:ingress10", "s3:egress3", "s9:ingress1", "s9:egress6", "s8:ingress3", "s8:egress20", "s26:ingress6", "s26:egress7"]}, "s16": {"s3": ["s16:ingress7", "s16:egress6", "s8:ingress10", "s8:egress20", "s26:ingress6", "s26:egress7"]}}, "h91": {"s3": {"s9": ["s16:ingress7", "s16:egress1", "s3:ingress10", "s3:egress12", "s18:ingress1", "s18:egress6", "s8:ingress12", "s8:egress3", "s9:ingress6", "s9:egress7"]}, "s16": {"s3": ["s16:ingress7", "s16:egress6", "s8:ingress10", "s8:egress3", "s9:ingress6", "s9:egress7"]}}, "h231": {"s3": {"s23": ["s16:ingress7", "s16:egress1", "s3:ingress10", "s3:egress3", "s9:ingress1", "s9:egress6", "s8:ingress3", "s8:egress17", "s23:ingress6", "s23:egress7"]}, "s16": {"s3": ["s16:ingress7", "s16:egress6", "s8:ingress10", "s8:egress17", "s23:ingress6", "s23:egress7"]}}, "h191": {"s3": {"s19": ["s16:ingress7", "s16:egress1", "s3:ingress10", "s3:egress3", "s9:ingress1", "s9:egress6", "s8:ingress3", "s8:egress13", "s19:ingress6", "s19:egress7"]}, "s16": {"s3": ["s16:ingress7", "s16:egress6", "s8:ingress10", "s8:egress13", "s19:ingress6", "s19:egress7"]}}, "h101": {"s3": {"s10": ["s16:ingress7", "s16:egress1", "s3:ingress10", "s3:egress3", "s9:ingress1", "s9:egress6", "s8:ingress3", "s8:egress4", "s10:ingress6", "s10:egress7"]}, "s16": {"s3": ["s16:ingress7", "s16:egress6", "s8:ingress10", "s8:egress4", "s10:ingress6", "s10:egress7"]}}, "h221": {"s3": {"s22": ["s16:ingress7", "s16:egress1", "s3:ingress10", "s3:egress3", "s9:ingress1", "s9:egress6", "s8:ingress3", "s8:egress16", "s22:ingress6", "s22:egress7"]}, "s16": {"s3": ["s16:ingress7", "s16:egress6", "s8:ingress10", "s8:egress16", "s22:ingress6", "s22:egress7"]}}, "h141": {"s3": {"s14": ["s16:ingress7", "s16:egress1", "s3:ingress10", "s3:egress3", "s9:ingress1", "s9:egress6", "s8:ingress3", "s8:egress8", "s14:ingress6", "s14:egress7"]}, "s16": {"s3": ["s16:ingress7", "s16:egress6", "s8:ingress10", "s8:egress8", "s14:ingress6", "s14:egress7"]}}, "h251": {"s3": {"s25": ["s16:ingress7", "s16:egress1", "s3:ingress10", "s3:egress3", "s9:ingress1", "s9:egress6", "s8:ingress3", "s8:egress19", "s25:ingress6", "s25:egress7"]}, "s16": {"s3": ["s16:ingress7", "s16:egress6", "s8:ingress10", "s8:egress19", "s25:ingress6", "s25:egress7"]}}, "h201": {"s3": {"s20": ["s16:ingress7", "s16:egress1", "s3:ingress10", "s3:egress3", "s9:ingress1", "s9:egress6", "s8:ingress3", "s8:egress14", "s20:ingress6", "s20:egress7"]}, "s16": {"s3": ["s16:ingress7", "s16:egress6", "s8:ingress10", "s8:egress14", "s20:ingress6", "s20:egress7"]}}, "h181": {"s3": {"s18": ["s16:ingress7", "s16:egress1", "s3:ingress10", "s3:egress3", "s9:ingress1", "s9:egress6", "s8:ingress3", "s8:egress12", "s18:ingress6", "s18:egress7"]}, "s16": {"s3": ["s16:ingress7", "s16:egress6", "s8:ingress10", "s8:egress12", "s18:ingress6", "s18:egress7"]}}, "h211": {"s3": {"s21": ["s16:ingress7", "s16:egress1", "s3:ingress10", "s3:egress3", "s9:ingress1", "s9:egress6", "s8:ingress3", "s8:egress15", "s21:ingress6", "s21:egress7"]}, "s16": {"s3": ["s16:ingress7", "s16:egress6", "s8:ingress10", "s8:egress15", "s21:ingress6", "s21:egress7"]}}, "h151": {"s3": {"s15": ["s16:ingress7", "s16:egress1", "s3:ingress10", "s3:egress3", "s9:ingress1", "s9:egress6", "s8:ingress3", "s8:egress9", "s15:ingress6", "s15:egress7"]}, "s16": {"s3": ["s16:ingress7", "s16:egress6", "s8:ingress10", "s8:egress9", "s15:ingress6", "s15:egress7"]}}}, "h191": {"h241": {"s3": {"s24": ["s19:ingress7", "s19:egress1", "s3:ingress13", "s3:egress3", "s9:ingress1", "s9:egress6", "s8:ingress3", "s8:egress18", "s24:ingress6", "s24:egress7"]}, "s19": {"s3": ["s19:ingress7", "s19:egress6", "s8:ingress13", "s8:egress18", "s24:ingress6", "s24:egress7"]}}, "h231": {"s3": {"s23": ["s19:ingress7", "s19:egress1", "s3:ingress13", "s3:egress3", "s9:ingress1", "s9:egress6", "s8:ingress3", "s8:egress17", "s23:ingress6", "s23:egress7"]}, "s19": {"s3": ["s19:ingress7", "s19:egress6", "s8:ingress13", "s8:egress17", "s23:ingress6", "s23:egress7"]}}, "h171": {"s3": {"s17": ["s19:ingress7", "s19:egress1", "s3:ingress13", "s3:egress3", "s9:ingress1", "s9:egress6", "s8:ingress3", "s8:egress11", "s17:ingress6", "s17:egress7"]}, "s19": {"s3": ["s19:ingress7", "s19:egress6", "s8:ingress13", "s8:egress11", "s17:ingress6", "s17:egress7"]}}, "h111": {"s3": {"s11": ["s19:ingress7", "s19:egress1", "s3:ingress13", "s3:egress3", "s9:ingress1", "s9:egress6", "s8:ingress3", "s8:egress5", "s11:ingress6", "s11:egress7"]}, "s19": {"s3": ["s19:ingress7", "s19:egress6", "s8:ingress13", "s8:egress5", "s11:ingress6", "s11:egress7"]}}, "h131": {"s3": {"s13": ["s19:ingress7", "s19:egress1", "s3:ingress13", "s3:egress3", "s9:ingress1", "s9:egress6", "s8:ingress3", "s8:egress7", "s13:ingress6", "s13:egress7"]}, "s19": {"s3": ["s19:ingress7", "s19:egress6", "s8:ingress13", "s8:egress7", "s13:ingress6", "s13:egress7"]}}, "h121": {"s3": {"s12": ["s19:ingress7", "s19:egress1", "s3:ingress13", "s3:egress3", "s9:ingress1", "s9:egress6", "s8:ingress3", "s8:egress6", "s12:ingress6", "s12:egress7"]}, "s19": {"s3": ["s19:ingress7", "s19:egress6", "s8:ingress13", "s8:egress6", "s12:ingress6", "s12:egress7"]}}, "h261": {"s3": {"s26": ["s19:ingress7", "s19:egress1", "s3:ingress13", "s3:egress3", "s9:ingress1", "s9:egress6", "s8:ingress3", "s8:egress20", "s26:ingress6", "s26:egress7"]}, "s19": {"s3": ["s19:ingress7", "s19:egress6", "s8:ingress13", "s8:egress20", "s26:ingress6", "s26:egress7"]}}, "h91": {"s3": {"s9": ["s19:ingress7", "s19:egress1", "s3:ingress13", "s3:egress12", "s18:ingress1", "s18:egress6", "s8:ingress12", "s8:egress3", "s9:ingress6", "s9:egress7"]}, "s19": {"s3": ["s19:ingress7", "s19:egress6", "s8:ingress13", "s8:egress3", "s9:ingress6", "s9:egress7"]}}, "h161": {"s3": {"s16": ["s19:ingress7", "s19:egress1", "s3:ingress13", "s3:egress3", "s9:ingress1", "s9:egress6", "s8:ingress3", "s8:egress10", "s16:ingress6", "s16:egress7"]}, "s19": {"s3": ["s19:ingress7", "s19:egress6", "s8:ingress13", "s8:egress10", "s16:ingress6", "s16:egress7"]}}, "h101": {"s3": {"s10": ["s19:ingress7", "s19:egress1", "s3:ingress13", "s3:egress3", "s9:ingress1", "s9:egress6", "s8:ingress3", "s8:egress4", "s10:ingress6", "s10:egress7"]}, "s19": {"s3": ["s19:ingress7", "s19:egress6", "s8:ingress13", "s8:egress4", "s10:ingress6", "s10:egress7"]}}, "h221": {"s3": {"s22": ["s19:ingress7", "s19:egress1", "s3:ingress13", "s3:egress3", "s9:ingress1", "s9:egress6", "s8:ingress3", "s8:egress16", "s22:ingress6", "s22:egress7"]}, "s19": {"s3": ["s19:ingress7", "s19:egress6", "s8:ingress13", "s8:egress16", "s22:ingress6", "s22:egress7"]}}, "h141": {"s3": {"s14": ["s19:ingress7", "s19:egress1", "s3:ingress13", "s3:egress3", "s9:ingress1", "s9:egress6", "s8:ingress3", "s8:egress8", "s14:ingress6", "s14:egress7"]}, "s19": {"s3": ["s19:ingress7", "s19:egress6", "s8:ingress13", "s8:egress8", "s14:ingress6", "s14:egress7"]}}, "h251": {"s3": {"s25": ["s19:ingress7", "s19:egress1", "s3:ingress13", "s3:egress3", "s9:ingress1", "s9:egress6", "s8:ingress3", "s8:egress19", "s25:ingress6", "s25:egress7"]}, "s19": {"s3": ["s19:ingress7", "s19:egress6", "s8:ingress13", "s8:egress19", "s25:ingress6", "s25:egress7"]}}, "h201": {"s3": {"s20": ["s19:ingress7", "s19:egress1", "s3:ingress13", "s3:egress3", "s9:ingress1", "s9:egress6", "s8:ingress3", "s8:egress14", "s20:ingress6", "s20:egress7"]}, "s19": {"s3": ["s19:ingress7", "s19:egress6", "s8:ingress13", "s8:egress14", "s20:ingress6", "s20:egress7"]}}, "h181": {"s3": {"s18": ["s19:ingress7", "s19:egress1", "s3:ingress13", "s3:egress3", "s9:ingress1", "s9:egress6", "s8:ingress3", "s8:egress12", "s18:ingress6", "s18:egress7"]}, "s19": {"s3": ["s19:ingress7", "s19:egress6", "s8:ingress13", "s8:egress12", "s18:ingress6", "s18:egress7"]}}, "h211": {"s3": {"s21": ["s19:ingress7", "s19:egress1", "s3:ingress13", "s3:egress3", "s9:ingress1", "s9:egress6", "s8:ingress3", "s8:egress15", "s21:ingress6", "s21:egress7"]}, "s19": {"s3": ["s19:ingress7", "s19:egress6", "s8:ingress13", "s8:egress15", "s21:ingress6", "s21:egress7"]}}, "h151": {"s3": {"s15": ["s19:ingress7", "s19:egress1", "s3:ingress13", "s3:egress3", "s9:ingress1", "s9:egress6", "s8:ingress3", "s8:egress9", "s15:ingress6", "s15:egress7"]}, "s19": {"s3": ["s19:ingress7", "s19:egress6", "s8:ingress13", "s8:egress9", "s15:ingress6", "s15:egress7"]}}}, "h101": {"h241": {"s3": {"s24": ["s10:ingress7", "s10:egress1", "s3:ingress4", "s3:egress3", "s9:ingress1", "s9:egress6", "s8:ingress3", "s8:egress18", "s24:ingress6", "s24:egress7"]}, "s10": {"s3": ["s10:ingress7", "s10:egress6", "s8:ingress4", "s8:egress18", "s24:ingress6", "s24:egress7"]}}, "h231": {"s3": {"s23": ["s10:ingress7", "s10:egress1", "s3:ingress4", "s3:egress3", "s9:ingress1", "s9:egress6", "s8:ingress3", "s8:egress17", "s23:ingress6", "s23:egress7"]}, "s10": {"s3": ["s10:ingress7", "s10:egress6", "s8:ingress4", "s8:egress17", "s23:ingress6", "s23:egress7"]}}, "h171": {"s3": {"s17": ["s10:ingress7", "s10:egress1", "s3:ingress4", "s3:egress3", "s9:ingress1", "s9:egress6", "s8:ingress3", "s8:egress11", "s17:ingress6", "s17:egress7"]}, "s10": {"s3": ["s10:ingress7", "s10:egress6", "s8:ingress4", "s8:egress11", "s17:ingress6", "s17:egress7"]}}, "h111": {"s3": {"s11": ["s10:ingress7", "s10:egress1", "s3:ingress4", "s3:egress3", "s9:ingress1", "s9:egress6", "s8:ingress3", "s8:egress5", "s11:ingress6", "s11:egress7"]}, "s10": {"s3": ["s10:ingress7", "s10:egress6", "s8:ingress4", "s8:egress5", "s11:ingress6", "s11:egress7"]}}, "h131": {"s3": {"s13": ["s10:ingress7", "s10:egress1", "s3:ingress4", "s3:egress3", "s9:ingress1", "s9:egress6", "s8:ingress3", "s8:egress7", "s13:ingress6", "s13:egress7"]}, "s10": {"s3": ["s10:ingress7", "s10:egress6", "s8:ingress4", "s8:egress7", "s13:ingress6", "s13:egress7"]}}, "h121": {"s3": {"s12": ["s10:ingress7", "s10:egress1", "s3:ingress4", "s3:egress3", "s9:ingress1", "s9:egress6", "s8:ingress3", "s8:egress6", "s12:ingress6", "s12:egress7"]}, "s10": {"s3": ["s10:ingress7", "s10:egress6", "s8:ingress4", "s8:egress6", "s12:ingress6", "s12:egress7"]}}, "h261": {"s3": {"s26": ["s10:ingress7", "s10:egress1", "s3:ingress4", "s3:egress3", "s9:ingress1", "s9:egress6", "s8:ingress3", "s8:egress20", "s26:ingress6", "s26:egress7"]}, "s10": {"s3": ["s10:ingress7", "s10:egress6", "s8:ingress4", "s8:egress20", "s26:ingress6", "s26:egress7"]}}, "h91": {"s3": {"s9": ["s10:ingress7", "s10:egress1", "s3:ingress4", "s3:egress12", "s18:ingress1", "s18:egress6", "s8:ingress12", "s8:egress3", "s9:ingress6", "s9:egress7"]}, "s10": {"s3": ["s10:ingress7", "s10:egress6", "s8:ingress4", "s8:egress3", "s9:ingress6", "s9:egress7"]}}, "h161": {"s3": {"s16": ["s10:ingress7", "s10:egress1", "s3:ingress4", "s3:egress3", "s9:ingress1", "s9:egress6", "s8:ingress3", "s8:egress10", "s16:ingress6", "s16:egress7"]}, "s10": {"s3": ["s10:ingress7", "s10:egress6", "s8:ingress4", "s8:egress10", "s16:ingress6", "s16:egress7"]}}, "h191": {"s3": {"s19": ["s10:ingress7", "s10:egress1", "s3:ingress4", "s3:egress3", "s9:ingress1", "s9:egress6", "s8:ingress3", "s8:egress13", "s19:ingress6", "s19:egress7"]}, "s10": {"s3": ["s10:ingress7", "s10:egress6", "s8:ingress4", "s8:egress13", "s19:ingress6", "s19:egress7"]}}, "h251": {"s3": {"s25": ["s10:ingress7", "s10:egress1", "s3:ingress4", "s3:egress3", "s9:ingress1", "s9:egress6", "s8:ingress3", "s8:egress19", "s25:ingress6", "s25:egress7"]}, "s10": {"s3": ["s10:ingress7", "s10:egress6", "s8:ingress4", "s8:egress19", "s25:ingress6", "s25:egress7"]}}, "h221": {"s3": {"s22": ["s10:ingress7", "s10:egress1", "s3:ingress4", "s3:egress3", "s9:ingress1", "s9:egress6", "s8:ingress3", "s8:egress16", "s22:ingress6", "s22:egress7"]}, "s10": {"s3": ["s10:ingress7", "s10:egress6", "s8:ingress4", "s8:egress16", "s22:ingress6", "s22:egress7"]}}, "h141": {"s3": {"s14": ["s10:ingress7", "s10:egress1", "s3:ingress4", "s3:egress3", "s9:ingress1", "s9:egress6", "s8:ingress3", "s8:egress8", "s14:ingress6", "s14:egress7"]}, "s10": {"s3": ["s10:ingress7", "s10:egress6", "s8:ingress4", "s8:egress8", "s14:ingress6", "s14:egress7"]}}, "h201": {"s3": {"s20": ["s10:ingress7", "s10:egress1", "s3:ingress4", "s3:egress3", "s9:ingress1", "s9:egress6", "s8:ingress3", "s8:egress14", "s20:ingress6", "s20:egress7"]}, "s10": {"s3": ["s10:ingress7", "s10:egress6", "s8:ingress4", "s8:egress14", "s20:ingress6", "s20:egress7"]}}, "h181": {"s3": {"s18": ["s10:ingress7", "s10:egress1", "s3:ingress4", "s3:egress3", "s9:ingress1", "s9:egress6", "s8:ingress3", "s8:egress12", "s18:ingress6", "s18:egress7"]}, "s10": {"s3": ["s10:ingress7", "s10:egress6", "s8:ingress4", "s8:egress12", "s18:ingress6", "s18:egress7"]}}, "h211": {"s3": {"s21": ["s10:ingress7", "s10:egress1", "s3:ingress4", "s3:egress3", "s9:ingress1", "s9:egress6", "s8:ingress3", "s8:egress15", "s21:ingress6", "s21:egress7"]}, "s10": {"s3": ["s10:ingress7", "s10:egress6", "s8:ingress4", "s8:egress15", "s21:ingress6", "s21:egress7"]}}, "h151": {"s3": {"s15": ["s10:ingress7", "s10:egress1", "s3:ingress4", "s3:egress3", "s9:ingress1", "s9:egress6", "s8:ingress3", "s8:egress9", "s15:ingress6", "s15:egress7"]}, "s10": {"s3": ["s10:ingress7", "s10:egress6", "s8:ingress4", "s8:egress9", "s15:ingress6", "s15:egress7"]}}}, "h221": {"h241": {"s22": {"s3": ["s22:ingress7", "s22:egress6", "s8:ingress16", "s8:egress18", "s24:ingress6", "s24:egress7"]}, "s3": {"s24": ["s22:ingress7", "s22:egress1", "s3:ingress16", "s3:egress3", "s9:ingress1", "s9:egress6", "s8:ingress3", "s8:egress18", "s24:ingress6", "s24:egress7"]}}, "h231": {"s22": {"s3": ["s22:ingress7", "s22:egress6", "s8:ingress16", "s8:egress17", "s23:ingress6", "s23:egress7"]}, "s3": {"s23": ["s22:ingress7", "s22:egress1", "s3:ingress16", "s3:egress3", "s9:ingress1", "s9:egress6", "s8:ingress3", "s8:egress17", "s23:ingress6", "s23:egress7"]}}, "h171": {"s22": {"s3": ["s22:ingress7", "s22:egress6", "s8:ingress16", "s8:egress11", "s17:ingress6", "s17:egress7"]}, "s3": {"s17": ["s22:ingress7", "s22:egress1", "s3:ingress16", "s3:egress3", "s9:ingress1", "s9:egress6", "s8:ingress3", "s8:egress11", "s17:ingress6", "s17:egress7"]}}, "h111": {"s22": {"s3": ["s22:ingress7", "s22:egress6", "s8:ingress16", "s8:egress5", "s11:ingress6", "s11:egress7"]}, "s3": {"s11": ["s22:ingress7", "s22:egress1", "s3:ingress16", "s3:egress3", "s9:ingress1", "s9:egress6", "s8:ingress3", "s8:egress5", "s11:ingress6", "s11:egress7"]}}, "h131": {"s22": {"s3": ["s22:ingress7", "s22:egress6", "s8:ingress16", "s8:egress7", "s13:ingress6", "s13:egress7"]}, "s3": {"s13": ["s22:ingress7", "s22:egress1", "s3:ingress16", "s3:egress3", "s9:ingress1", "s9:egress6", "s8:ingress3", "s8:egress7", "s13:ingress6", "s13:egress7"]}}, "h121": {"s22": {"s3": ["s22:ingress7", "s22:egress6", "s8:ingress16", "s8:egress6", "s12:ingress6", "s12:egress7"]}, "s3": {"s12": ["s22:ingress7", "s22:egress1", "s3:ingress16", "s3:egress3", "s9:ingress1", "s9:egress6", "s8:ingress3", "s8:egress6", "s12:ingress6", "s12:egress7"]}}, "h261": {"s22": {"s3": ["s22:ingress7", "s22:egress6", "s8:ingress16", "s8:egress20", "s26:ingress6", "s26:egress7"]}, "s3": {"s26": ["s22:ingress7", "s22:egress1", "s3:ingress16", "s3:egress3", "s9:ingress1", "s9:egress6", "s8:ingress3", "s8:egress20", "s26:ingress6", "s26:egress7"]}}, "h91": {"s22": {"s3": ["s22:ingress7", "s22:egress6", "s8:ingress16", "s8:egress3", "s9:ingress6", "s9:egress7"]}, "s3": {"s9": ["s22:ingress7", "s22:egress1", "s3:ingress16", "s3:egress12", "s18:ingress1", "s18:egress6", "s8:ingress12", "s8:egress3", "s9:ingress6", "s9:egress7"]}}, "h161": {"s22": {"s3": ["s22:ingress7", "s22:egress6", "s8:ingress16", "s8:egress10", "s16:ingress6", "s16:egress7"]}, "s3": {"s16": ["s22:ingress7", "s22:egress1", "s3:ingress16", "s3:egress3", "s9:ingress1", "s9:egress6", "s8:ingress3", "s8:egress10", "s16:ingress6", "s16:egress7"]}}, "h191": {"s22": {"s3": ["s22:ingress7", "s22:egress6", "s8:ingress16", "s8:egress13", "s19:ingress6", "s19:egress7"]}, "s3": {"s19": ["s22:ingress7", "s22:egress1", "s3:ingress16", "s3:egress3", "s9:ingress1", "s9:egress6", "s8:ingress3", "s8:egress13", "s19:ingress6", "s19:egress7"]}}, "h101": {"s22": {"s3": ["s22:ingress7", "s22:egress6", "s8:ingress16", "s8:egress4", "s10:ingress6", "s10:egress7"]}, "s3": {"s10": ["s22:ingress7", "s22:egress1", "s3:ingress16", "s3:egress3", "s9:ingress1", "s9:egress6", "s8:ingress3", "s8:egress4", "s10:ingress6", "s10:egress7"]}}, "h141": {"s22": {"s3": ["s22:ingress7", "s22:egress6", "s8:ingress16", "s8:egress8", "s14:ingress6", "s14:egress7"]}, "s3": {"s14": ["s22:ingress7", "s22:egress1", "s3:ingress16", "s3:egress3", "s9:ingress1", "s9:egress6", "s8:ingress3", "s8:egress8", "s14:ingress6", "s14:egress7"]}}, "h251": {"s22": {"s3": ["s22:ingress7", "s22:egress6", "s8:ingress16", "s8:egress19", "s25:ingress6", "s25:egress7"]}, "s3": {"s25": ["s22:ingress7", "s22:egress1", "s3:ingress16", "s3:egress3", "s9:ingress1", "s9:egress6", "s8:ingress3", "s8:egress19", "s25:ingress6", "s25:egress7"]}}, "h201": {"s22": {"s3": ["s22:ingress7", "s22:egress6", "s8:ingress16", "s8:egress14", "s20:ingress6", "s20:egress7"]}, "s3": {"s20": ["s22:ingress7", "s22:egress1", "s3:ingress16", "s3:egress3", "s9:ingress1", "s9:egress6", "s8:ingress3", "s8:egress14", "s20:ingress6", "s20:egress7"]}}, "h181": {"s22": {"s3": ["s22:ingress7", "s22:egress6", "s8:ingress16", "s8:egress12", "s18:ingress6", "s18:egress7"]}, "s3": {"s18": ["s22:ingress7", "s22:egress1", "s3:ingress16", "s3:egress3", "s9:ingress1", "s9:egress6", "s8:ingress3", "s8:egress12", "s18:ingress6", "s18:egress7"]}}, "h211": {"s22": {"s3": ["s22:ingress7", "s22:egress6", "s8:ingress16", "s8:egress15", "s21:ingress6", "s21:egress7"]}, "s3": {"s21": ["s22:ingress7", "s22:egress1", "s3:ingress16", "s3:egress3", "s9:ingress1", "s9:egress6", "s8:ingress3", "s8:egress15", "s21:ingress6", "s21:egress7"]}}, "h151": {"s22": {"s3": ["s22:ingress7", "s22:egress6", "s8:ingress16", "s8:egress9", "s15:ingress6", "s15:egress7"]}, "s3": {"s15": ["s22:ingress7", "s22:egress1", "s3:ingress16", "s3:egress3", "s9:ingress1", "s9:egress6", "s8:ingress3", "s8:egress9", "s15:ingress6", "s15:egress7"]}}}, "h141": {"h241": {"s3": {"s24": ["s14:ingress7", "s14:egress1", "s3:ingress8", "s3:egress3", "s9:ingress1", "s9:egress6", "s8:ingress3", "s8:egress18", "s24:ingress6", "s24:egress7"]}, "s14": {"s3": ["s14:ingress7", "s14:egress6", "s8:ingress8", "s8:egress18", "s24:ingress6", "s24:egress7"]}}, "h231": {"s3": {"s23": ["s14:ingress7", "s14:egress1", "s3:ingress8", "s3:egress3", "s9:ingress1", "s9:egress6", "s8:ingress3", "s8:egress17", "s23:ingress6", "s23:egress7"]}, "s14": {"s3": ["s14:ingress7", "s14:egress6", "s8:ingress8", "s8:egress17", "s23:ingress6", "s23:egress7"]}}, "h171": {"s3": {"s17": ["s14:ingress7", "s14:egress1", "s3:ingress8", "s3:egress3", "s9:ingress1", "s9:egress6", "s8:ingress3", "s8:egress11", "s17:ingress6", "s17:egress7"]}, "s14": {"s3": ["s14:ingress7", "s14:egress6", "s8:ingress8", "s8:egress11", "s17:ingress6", "s17:egress7"]}}, "h111": {"s3": {"s11": ["s14:ingress7", "s14:egress1", "s3:ingress8", "s3:egress3", "s9:ingress1", "s9:egress6", "s8:ingress3", "s8:egress5", "s11:ingress6", "s11:egress7"]}, "s14": {"s3": ["s14:ingress7", "s14:egress6", "s8:ingress8", "s8:egress5", "s11:ingress6", "s11:egress7"]}}, "h131": {"s3": {"s13": ["s14:ingress7", "s14:egress1", "s3:ingress8", "s3:egress3", "s9:ingress1", "s9:egress6", "s8:ingress3", "s8:egress7", "s13:ingress6", "s13:egress7"]}, "s14": {"s3": ["s14:ingress7", "s14:egress6", "s8:ingress8", "s8:egress7", "s13:ingress6", "s13:egress7"]}}, "h121": {"s3": {"s12": ["s14:ingress7", "s14:egress1", "s3:ingress8", "s3:egress3", "s9:ingress1", "s9:egress6", "s8:ingress3", "s8:egress6", "s12:ingress6", "s12:egress7"]}, "s14": {"s3": ["s14:ingress7", "s14:egress6", "s8:ingress8", "s8:egress6", "s12:ingress6", "s12:egress7"]}}, "h261": {"s3": {"s26": ["s14:ingress7", "s14:egress1", "s3:ingress8", "s3:egress3", "s9:ingress1", "s9:egress6", "s8:ingress3", "s8:egress20", "s26:ingress6", "s26:egress7"]}, "s14": {"s3": ["s14:ingress7", "s14:egress6", "s8:ingress8", "s8:egress20", "s26:ingress6", "s26:egress7"]}}, "h91": {"s3": {"s9": ["s14:ingress7", "s14:egress1", "s3:ingress8", "s3:egress12", "s18:ingress1", "s18:egress6", "s8:ingress12", "s8:egress3", "s9:ingress6", "s9:egress7"]}, "s14": {"s3": ["s14:ingress7", "s14:egress6", "s8:ingress8", "s8:egress3", "s9:ingress6", "s9:egress7"]}}, "h161": {"s3": {"s16": ["s14:ingress7", "s14:egress1", "s3:ingress8", "s3:egress3", "s9:ingress1", "s9:egress6", "s8:ingress3", "s8:egress10", "s16:ingress6", "s16:egress7"]}, "s14": {"s3": ["s14:ingress7", "s14:egress6", "s8:ingress8", "s8:egress10", "s16:ingress6", "s16:egress7"]}}, "h191": {"s3": {"s19": ["s14:ingress7", "s14:egress1", "s3:ingress8", "s3:egress3", "s9:ingress1", "s9:egress6", "s8:ingress3", "s8:egress13", "s19:ingress6", "s19:egress7"]}, "s14": {"s3": ["s14:ingress7", "s14:egress6", "s8:ingress8", "s8:egress13", "s19:ingress6", "s19:egress7"]}}, "h101": {"s3": {"s10": ["s14:ingress7", "s14:egress1", "s3:ingress8", "s3:egress3", "s9:ingress1", "s9:egress6", "s8:ingress3", "s8:egress4", "s10:ingress6", "s10:egress7"]}, "s14": {"s3": ["s14:ingress7", "s14:egress6", "s8:ingress8", "s8:egress4", "s10:ingress6", "s10:egress7"]}}, "h221": {"s3": {"s22": ["s14:ingress7", "s14:egress1", "s3:ingress8", "s3:egress3", "s9:ingress1", "s9:egress6", "s8:ingress3", "s8:egress16", "s22:ingress6", "s22:egress7"]}, "s14": {"s3": ["s14:ingress7", "s14:egress6", "s8:ingress8", "s8:egress16", "s22:ingress6", "s22:egress7"]}}, "h211": {"s3": {"s21": ["s14:ingress7", "s14:egress1", "s3:ingress8", "s3:egress3", "s9:ingress1", "s9:egress6", "s8:ingress3", "s8:egress15", "s21:ingress6", "s21:egress7"]}, "s14": {"s3": ["s14:ingress7", "s14:egress6", "s8:ingress8", "s8:egress15", "s21:ingress6", "s21:egress7"]}}, "h251": {"s3": {"s25": ["s14:ingress7", "s14:egress1", "s3:ingress8", "s3:egress3", "s9:ingress1", "s9:egress6", "s8:ingress3", "s8:egress19", "s25:ingress6", "s25:egress7"]}, "s14": {"s3": ["s14:ingress7", "s14:egress6", "s8:ingress8", "s8:egress19", "s25:ingress6", "s25:egress7"]}}, "h201": {"s3": {"s20": ["s14:ingress7", "s14:egress1", "s3:ingress8", "s3:egress3", "s9:ingress1", "s9:egress6", "s8:ingress3", "s8:egress14", "s20:ingress6", "s20:egress7"]}, "s14": {"s3": ["s14:ingress7", "s14:egress6", "s8:ingress8", "s8:egress14", "s20:ingress6", "s20:egress7"]}}, "h181": {"s3": {"s18": ["s14:ingress7", "s14:egress1", "s3:ingress8", "s3:egress3", "s9:ingress1", "s9:egress6", "s8:ingress3", "s8:egress12", "s18:ingress6", "s18:egress7"]}, "s14": {"s3": ["s14:ingress7", "s14:egress6", "s8:ingress8", "s8:egress12", "s18:ingress6", "s18:egress7"]}}, "h151": {"s3": {"s15": ["s14:ingress7", "s14:egress1", "s3:ingress8", "s3:egress3", "s9:ingress1", "s9:egress6", "s8:ingress3", "s8:egress9", "s15:ingress6", "s15:egress7"]}, "s14": {"s3": ["s14:ingress7", "s14:egress6", "s8:ingress8", "s8:egress9", "s15:ingress6", "s15:egress7"]}}}, "h251": {"h241": {"s3": {"s24": ["s25:ingress7", "s25:egress1", "s3:ingress19", "s3:egress3", "s9:ingress1", "s9:egress6", "s8:ingress3", "s8:egress18", "s24:ingress6", "s24:egress7"]}, "s25": {"s3": ["s25:ingress7", "s25:egress6", "s8:ingress19", "s8:egress18", "s24:ingress6", "s24:egress7"]}}, "h231": {"s3": {"s23": ["s25:ingress7", "s25:egress1", "s3:ingress19", "s3:egress3", "s9:ingress1", "s9:egress6", "s8:ingress3", "s8:egress17", "s23:ingress6", "s23:egress7"]}, "s25": {"s3": ["s25:ingress7", "s25:egress6", "s8:ingress19", "s8:egress17", "s23:ingress6", "s23:egress7"]}}, "h171": {"s3": {"s17": ["s25:ingress7", "s25:egress1", "s3:ingress19", "s3:egress3", "s9:ingress1", "s9:egress6", "s8:ingress3", "s8:egress11", "s17:ingress6", "s17:egress7"]}, "s25": {"s3": ["s25:ingress7", "s25:egress6", "s8:ingress19", "s8:egress11", "s17:ingress6", "s17:egress7"]}}, "h111": {"s3": {"s11": ["s25:ingress7", "s25:egress1", "s3:ingress19", "s3:egress3", "s9:ingress1", "s9:egress6", "s8:ingress3", "s8:egress5", "s11:ingress6", "s11:egress7"]}, "s25": {"s3": ["s25:ingress7", "s25:egress6", "s8:ingress19", "s8:egress5", "s11:ingress6", "s11:egress7"]}}, "h131": {"s3": {"s13": ["s25:ingress7", "s25:egress1", "s3:ingress19", "s3:egress3", "s9:ingress1", "s9:egress6", "s8:ingress3", "s8:egress7", "s13:ingress6", "s13:egress7"]}, "s25": {"s3": ["s25:ingress7", "s25:egress6", "s8:ingress19", "s8:egress7", "s13:ingress6", "s13:egress7"]}}, "h121": {"s3": {"s12": ["s25:ingress7", "s25:egress1", "s3:ingress19", "s3:egress3", "s9:ingress1", "s9:egress6", "s8:ingress3", "s8:egress6", "s12:ingress6", "s12:egress7"]}, "s25": {"s3": ["s25:ingress7", "s25:egress6", "s8:ingress19", "s8:egress6", "s12:ingress6", "s12:egress7"]}}, "h261": {"s3": {"s26": ["s25:ingress7", "s25:egress1", "s3:ingress19", "s3:egress3", "s9:ingress1", "s9:egress6", "s8:ingress3", "s8:egress20", "s26:ingress6", "s26:egress7"]}, "s25": {"s3": ["s25:ingress7", "s25:egress6", "s8:ingress19", "s8:egress20", "s26:ingress6", "s26:egress7"]}}, "h91": {"s3": {"s9": ["s25:ingress7", "s25:egress1", "s3:ingress19", "s3:egress12", "s18:ingress1", "s18:egress6", "s8:ingress12", "s8:egress3", "s9:ingress6", "s9:egress7"]}, "s25": {"s3": ["s25:ingress7", "s25:egress6", "s8:ingress19", "s8:egress3", "s9:ingress6", "s9:egress7"]}}, "h161": {"s3": {"s16": ["s25:ingress7", "s25:egress1", "s3:ingress19", "s3:egress3", "s9:ingress1", "s9:egress6", "s8:ingress3", "s8:egress10", "s16:ingress6", "s16:egress7"]}, "s25": {"s3": ["s25:ingress7", "s25:egress6", "s8:ingress19", "s8:egress10", "s16:ingress6", "s16:egress7"]}}, "h191": {"s3": {"s19": ["s25:ingress7", "s25:egress1", "s3:ingress19", "s3:egress3", "s9:ingress1", "s9:egress6", "s8:ingress3", "s8:egress13", "s19:ingress6", "s19:egress7"]}, "s25": {"s3": ["s25:ingress7", "s25:egress6", "s8:ingress19", "s8:egress13", "s19:ingress6", "s19:egress7"]}}, "h101": {"s3": {"s10": ["s25:ingress7", "s25:egress1", "s3:ingress19", "s3:egress3", "s9:ingress1", "s9:egress6", "s8:ingress3", "s8:egress4", "s10:ingress6", "s10:egress7"]}, "s25": {"s3": ["s25:ingress7", "s25:egress6", "s8:ingress19", "s8:egress4", "s10:ingress6", "s10:egress7"]}}, "h221": {"s3": {"s22": ["s25:ingress7", "s25:egress1", "s3:ingress19", "s3:egress3", "s9:ingress1", "s9:egress6", "s8:ingress3", "s8:egress16", "s22:ingress6", "s22:egress7"]}, "s25": {"s3": ["s25:ingress7", "s25:egress6", "s8:ingress19", "s8:egress16", "s22:ingress6", "s22:egress7"]}}, "h141": {"s3": {"s14": ["s25:ingress7", "s25:egress1", "s3:ingress19", "s3:egress3", "s9:ingress1", "s9:egress6", "s8:ingress3", "s8:egress8", "s14:ingress6", "s14:egress7"]}, "s25": {"s3": ["s25:ingress7", "s25:egress6", "s8:ingress19", "s8:egress8", "s14:ingress6", "s14:egress7"]}}, "h201": {"s3": {"s20": ["s25:ingress7", "s25:egress1", "s3:ingress19", "s3:egress3", "s9:ingress1", "s9:egress6", "s8:ingress3", "s8:egress14", "s20:ingress6", "s20:egress7"]}, "s25": {"s3": ["s25:ingress7", "s25:egress6", "s8:ingress19", "s8:egress14", "s20:ingress6", "s20:egress7"]}}, "h181": {"s3": {"s18": ["s25:ingress7", "s25:egress1", "s3:ingress19", "s3:egress3", "s9:ingress1", "s9:egress6", "s8:ingress3", "s8:egress12", "s18:ingress6", "s18:egress7"]}, "s25": {"s3": ["s25:ingress7", "s25:egress6", "s8:ingress19", "s8:egress12", "s18:ingress6", "s18:egress7"]}}, "h211": {"s3": {"s21": ["s25:ingress7", "s25:egress1", "s3:ingress19", "s3:egress3", "s9:ingress1", "s9:egress6", "s8:ingress3", "s8:egress15", "s21:ingress6", "s21:egress7"]}, "s25": {"s3": ["s25:ingress7", "s25:egress6", "s8:ingress19", "s8:egress15", "s21:ingress6", "s21:egress7"]}}, "h151": {"s3": {"s15": ["s25:ingress7", "s25:egress1", "s3:ingress19", "s3:egress3", "s9:ingress1", "s9:egress6", "s8:ingress3", "s8:egress9", "s15:ingress6", "s15:egress7"]}, "s25": {"s3": ["s25:ingress7", "s25:egress6", "s8:ingress19", "s8:egress9", "s15:ingress6", "s15:egress7"]}}}, "h201": {"h241": {"s3": {"s24": ["s20:ingress7", "s20:egress1", "s3:ingress14", "s3:egress3", "s9:ingress1", "s9:egress6", "s8:ingress3", "s8:egress18", "s24:ingress6", "s24:egress7"]}, "s20": {"s3": ["s20:ingress7", "s20:egress6", "s8:ingress14", "s8:egress18", "s24:ingress6", "s24:egress7"]}}, "h231": {"s3": {"s23": ["s20:ingress7", "s20:egress1", "s3:ingress14", "s3:egress3", "s9:ingress1", "s9:egress6", "s8:ingress3", "s8:egress17", "s23:ingress6", "s23:egress7"]}, "s20": {"s3": ["s20:ingress7", "s20:egress6", "s8:ingress14", "s8:egress17", "s23:ingress6", "s23:egress7"]}}, "h171": {"s3": {"s17": ["s20:ingress7", "s20:egress1", "s3:ingress14", "s3:egress3", "s9:ingress1", "s9:egress6", "s8:ingress3", "s8:egress11", "s17:ingress6", "s17:egress7"]}, "s20": {"s3": ["s20:ingress7", "s20:egress6", "s8:ingress14", "s8:egress11", "s17:ingress6", "s17:egress7"]}}, "h111": {"s3": {"s11": ["s20:ingress7", "s20:egress1", "s3:ingress14", "s3:egress3", "s9:ingress1", "s9:egress6", "s8:ingress3", "s8:egress5", "s11:ingress6", "s11:egress7"]}, "s20": {"s3": ["s20:ingress7", "s20:egress6", "s8:ingress14", "s8:egress5", "s11:ingress6", "s11:egress7"]}}, "h131": {"s3": {"s13": ["s20:ingress7", "s20:egress1", "s3:ingress14", "s3:egress3", "s9:ingress1", "s9:egress6", "s8:ingress3", "s8:egress7", "s13:ingress6", "s13:egress7"]}, "s20": {"s3": ["s20:ingress7", "s20:egress6", "s8:ingress14", "s8:egress7", "s13:ingress6", "s13:egress7"]}}, "h121": {"s3": {"s12": ["s20:ingress7", "s20:egress1", "s3:ingress14", "s3:egress3", "s9:ingress1", "s9:egress6", "s8:ingress3", "s8:egress6", "s12:ingress6", "s12:egress7"]}, "s20": {"s3": ["s20:ingress7", "s20:egress6", "s8:ingress14", "s8:egress6", "s12:ingress6", "s12:egress7"]}}, "h261": {"s3": {"s26": ["s20:ingress7", "s20:egress1", "s3:ingress14", "s3:egress3", "s9:ingress1", "s9:egress6", "s8:ingress3", "s8:egress20", "s26:ingress6", "s26:egress7"]}, "s20": {"s3": ["s20:ingress7", "s20:egress6", "s8:ingress14", "s8:egress20", "s26:ingress6", "s26:egress7"]}}, "h91": {"s3": {"s9": ["s20:ingress7", "s20:egress1", "s3:ingress14", "s3:egress12", "s18:ingress1", "s18:egress6", "s8:ingress12", "s8:egress3", "s9:ingress6", "s9:egress7"]}, "s20": {"s3": ["s20:ingress7", "s20:egress6", "s8:ingress14", "s8:egress3", "s9:ingress6", "s9:egress7"]}}, "h161": {"s3": {"s16": ["s20:ingress7", "s20:egress1", "s3:ingress14", "s3:egress3", "s9:ingress1", "s9:egress6", "s8:ingress3", "s8:egress10", "s16:ingress6", "s16:egress7"]}, "s20": {"s3": ["s20:ingress7", "s20:egress6", "s8:ingress14", "s8:egress10", "s16:ingress6", "s16:egress7"]}}, "h191": {"s3": {"s19": ["s20:ingress7", "s20:egress1", "s3:ingress14", "s3:egress3", "s9:ingress1", "s9:egress6", "s8:ingress3", "s8:egress13", "s19:ingress6", "s19:egress7"]}, "s20": {"s3": ["s20:ingress7", "s20:egress6", "s8:ingress14", "s8:egress13", "s19:ingress6", "s19:egress7"]}}, "h101": {"s3": {"s10": ["s20:ingress7", "s20:egress1", "s3:ingress14", "s3:egress3", "s9:ingress1", "s9:egress6", "s8:ingress3", "s8:egress4", "s10:ingress6", "s10:egress7"]}, "s20": {"s3": ["s20:ingress7", "s20:egress6", "s8:ingress14", "s8:egress4", "s10:ingress6", "s10:egress7"]}}, "h221": {"s3": {"s22": ["s20:ingress7", "s20:egress1", "s3:ingress14", "s3:egress3", "s9:ingress1", "s9:egress6", "s8:ingress3", "s8:egress16", "s22:ingress6", "s22:egress7"]}, "s20": {"s3": ["s20:ingress7", "s20:egress6", "s8:ingress14", "s8:egress16", "s22:ingress6", "s22:egress7"]}}, "h141": {"s3": {"s14": ["s20:ingress7", "s20:egress1", "s3:ingress14", "s3:egress3", "s9:ingress1", "s9:egress6", "s8:ingress3", "s8:egress8", "s14:ingress6", "s14:egress7"]}, "s20": {"s3": ["s20:ingress7", "s20:egress6", "s8:ingress14", "s8:egress8", "s14:ingress6", "s14:egress7"]}}, "h251": {"s3": {"s25": ["s20:ingress7", "s20:egress1", "s3:ingress14", "s3:egress3", "s9:ingress1", "s9:egress6", "s8:ingress3", "s8:egress19", "s25:ingress6", "s25:egress7"]}, "s20": {"s3": ["s20:ingress7", "s20:egress6", "s8:ingress14", "s8:egress19", "s25:ingress6", "s25:egress7"]}}, "h181": {"s3": {"s18": ["s20:ingress7", "s20:egress1", "s3:ingress14", "s3:egress3", "s9:ingress1", "s9:egress6", "s8:ingress3", "s8:egress12", "s18:ingress6", "s18:egress7"]}, "s20": {"s3": ["s20:ingress7", "s20:egress6", "s8:ingress14", "s8:egress12", "s18:ingress6", "s18:egress7"]}}, "h211": {"s3": {"s21": ["s20:ingress7", "s20:egress1", "s3:ingress14", "s3:egress3", "s9:ingress1", "s9:egress6", "s8:ingress3", "s8:egress15", "s21:ingress6", "s21:egress7"]}, "s20": {"s3": ["s20:ingress7", "s20:egress6", "s8:ingress14", "s8:egress15", "s21:ingress6", "s21:egress7"]}}, "h151": {"s3": {"s15": ["s20:ingress7", "s20:egress1", "s3:ingress14", "s3:egress3", "s9:ingress1", "s9:egress6", "s8:ingress3", "s8:egress9", "s15:ingress6", "s15:egress7"]}, "s20": {"s3": ["s20:ingress7", "s20:egress6", "s8:ingress14", "s8:egress9", "s15:ingress6", "s15:egress7"]}}}, "h181": {"h241": {"s3": {"s24": ["s18:ingress7", "s18:egress1", "s3:ingress12", "s3:egress3", "s9:ingress1", "s9:egress6", "s8:ingress3", "s8:egress18", "s24:ingress6", "s24:egress7"]}, "s18": {"s3": ["s18:ingress7", "s18:egress6", "s8:ingress12", "s8:egress18", "s24:ingress6", "s24:egress7"]}}, "h231": {"s3": {"s23": ["s18:ingress7", "s18:egress1", "s3:ingress12", "s3:egress3", "s9:ingress1", "s9:egress6", "s8:ingress3", "s8:egress17", "s23:ingress6", "s23:egress7"]}, "s18": {"s3": ["s18:ingress7", "s18:egress6", "s8:ingress12", "s8:egress17", "s23:ingress6", "s23:egress7"]}}, "h171": {"s3": {"s17": ["s18:ingress7", "s18:egress1", "s3:ingress12", "s3:egress3", "s9:ingress1", "s9:egress6", "s8:ingress3", "s8:egress11", "s17:ingress6", "s17:egress7"]}, "s18": {"s3": ["s18:ingress7", "s18:egress6", "s8:ingress12", "s8:egress11", "s17:ingress6", "s17:egress7"]}}, "h111": {"s3": {"s11": ["s18:ingress7", "s18:egress1", "s3:ingress12", "s3:egress3", "s9:ingress1", "s9:egress6", "s8:ingress3", "s8:egress5", "s11:ingress6", "s11:egress7"]}, "s18": {"s3": ["s18:ingress7", "s18:egress6", "s8:ingress12", "s8:egress5", "s11:ingress6", "s11:egress7"]}}, "h131": {"s3": {"s13": ["s18:ingress7", "s18:egress1", "s3:ingress12", "s3:egress3", "s9:ingress1", "s9:egress6", "s8:ingress3", "s8:egress7", "s13:ingress6", "s13:egress7"]}, "s18": {"s3": ["s18:ingress7", "s18:egress6", "s8:ingress12", "s8:egress7", "s13:ingress6", "s13:egress7"]}}, "h121": {"s3": {"s12": ["s18:ingress7", "s18:egress1", "s3:ingress12", "s3:egress3", "s9:ingress1", "s9:egress6", "s8:ingress3", "s8:egress6", "s12:ingress6", "s12:egress7"]}, "s18": {"s3": ["s18:ingress7", "s18:egress6", "s8:ingress12", "s8:egress6", "s12:ingress6", "s12:egress7"]}}, "h261": {"s3": {"s26": ["s18:ingress7", "s18:egress1", "s3:ingress12", "s3:egress3", "s9:ingress1", "s9:egress6", "s8:ingress3", "s8:egress20", "s26:ingress6", "s26:egress7"]}, "s18": {"s3": ["s18:ingress7", "s18:egress6", "s8:ingress12", "s8:egress20", "s26:ingress6", "s26:egress7"]}}, "h91": {"s3": {"s9": ["s18:ingress7", "s18:egress1", "s3:ingress12", "s3:egress12", "s18:ingress1", "s18:egress6", "s8:ingress12", "s8:egress3", "s9:ingress6", "s9:egress7"]}, "s18": {"s3": ["s18:ingress7", "s18:egress6", "s8:ingress12", "s8:egress3", "s9:ingress6", "s9:egress7"]}}, "h161": {"s3": {"s16": ["s18:ingress7", "s18:egress1", "s3:ingress12", "s3:egress3", "s9:ingress1", "s9:egress6", "s8:ingress3", "s8:egress10", "s16:ingress6", "s16:egress7"]}, "s18": {"s3": ["s18:ingress7", "s18:egress6", "s8:ingress12", "s8:egress10", "s16:ingress6", "s16:egress7"]}}, "h191": {"s3": {"s19": ["s18:ingress7", "s18:egress1", "s3:ingress12", "s3:egress3", "s9:ingress1", "s9:egress6", "s8:ingress3", "s8:egress13", "s19:ingress6", "s19:egress7"]}, "s18": {"s3": ["s18:ingress7", "s18:egress6", "s8:ingress12", "s8:egress13", "s19:ingress6", "s19:egress7"]}}, "h101": {"s3": {"s10": ["s18:ingress7", "s18:egress1", "s3:ingress12", "s3:egress3", "s9:ingress1", "s9:egress6", "s8:ingress3", "s8:egress4", "s10:ingress6", "s10:egress7"]}, "s18": {"s3": ["s18:ingress7", "s18:egress6", "s8:ingress12", "s8:egress4", "s10:ingress6", "s10:egress7"]}}, "h221": {"s3": {"s22": ["s18:ingress7", "s18:egress1", "s3:ingress12", "s3:egress3", "s9:ingress1", "s9:egress6", "s8:ingress3", "s8:egress16", "s22:ingress6", "s22:egress7"]}, "s18": {"s3": ["s18:ingress7", "s18:egress6", "s8:ingress12", "s8:egress16", "s22:ingress6", "s22:egress7"]}}, "h141": {"s3": {"s14": ["s18:ingress7", "s18:egress1", "s3:ingress12", "s3:egress3", "s9:ingress1", "s9:egress6", "s8:ingress3", "s8:egress8", "s14:ingress6", "s14:egress7"]}, "s18": {"s3": ["s18:ingress7", "s18:egress6", "s8:ingress12", "s8:egress8", "s14:ingress6", "s14:egress7"]}}, "h251": {"s3": {"s25": ["s18:ingress7", "s18:egress1", "s3:ingress12", "s3:egress3", "s9:ingress1", "s9:egress6", "s8:ingress3", "s8:egress19", "s25:ingress6", "s25:egress7"]}, "s18": {"s3": ["s18:ingress7", "s18:egress6", "s8:ingress12", "s8:egress19", "s25:ingress6", "s25:egress7"]}}, "h201": {"s3": {"s20": ["s18:ingress7", "s18:egress1", "s3:ingress12", "s3:egress3", "s9:ingress1", "s9:egress6", "s8:ingress3", "s8:egress14", "s20:ingress6", "s20:egress7"]}, "s18": {"s3": ["s18:ingress7", "s18:egress6", "s8:ingress12", "s8:egress14", "s20:ingress6", "s20:egress7"]}}, "h211": {"s3": {"s21": ["s18:ingress7", "s18:egress1", "s3:ingress12", "s3:egress3", "s9:ingress1", "s9:egress6", "s8:ingress3", "s8:egress15", "s21:ingress6", "s21:egress7"]}, "s18": {"s3": ["s18:ingress7", "s18:egress6", "s8:ingress12", "s8:egress15", "s21:ingress6", "s21:egress7"]}}, "h151": {"s3": {"s15": ["s18:ingress7", "s18:egress1", "s3:ingress12", "s3:egress3", "s9:ingress1", "s9:egress6", "s8:ingress3", "s8:egress9", "s15:ingress6", "s15:egress7"]}, "s18": {"s3": ["s18:ingress7", "s18:egress6", "s8:ingress12", "s8:egress9", "s15:ingress6", "s15:egress7"]}}}, "h211": {"h241": {"s3": {"s24": ["s21:ingress7", "s21:egress1", "s3:ingress15", "s3:egress3", "s9:ingress1", "s9:egress6", "s8:ingress3", "s8:egress18", "s24:ingress6", "s24:egress7"]}, "s21": {"s3": ["s21:ingress7", "s21:egress6", "s8:ingress15", "s8:egress18", "s24:ingress6", "s24:egress7"]}}, "h231": {"s3": {"s23": ["s21:ingress7", "s21:egress1", "s3:ingress15", "s3:egress3", "s9:ingress1", "s9:egress6", "s8:ingress3", "s8:egress17", "s23:ingress6", "s23:egress7"]}, "s21": {"s3": ["s21:ingress7", "s21:egress6", "s8:ingress15", "s8:egress17", "s23:ingress6", "s23:egress7"]}}, "h171": {"s3": {"s17": ["s21:ingress7", "s21:egress1", "s3:ingress15", "s3:egress3", "s9:ingress1", "s9:egress6", "s8:ingress3", "s8:egress11", "s17:ingress6", "s17:egress7"]}, "s21": {"s3": ["s21:ingress7", "s21:egress6", "s8:ingress15", "s8:egress11", "s17:ingress6", "s17:egress7"]}}, "h111": {"s3": {"s11": ["s21:ingress7", "s21:egress1", "s3:ingress15", "s3:egress3", "s9:ingress1", "s9:egress6", "s8:ingress3", "s8:egress5", "s11:ingress6", "s11:egress7"]}, "s21": {"s3": ["s21:ingress7", "s21:egress6", "s8:ingress15", "s8:egress5", "s11:ingress6", "s11:egress7"]}}, "h131": {"s3": {"s13": ["s21:ingress7", "s21:egress1", "s3:ingress15", "s3:egress3", "s9:ingress1", "s9:egress6", "s8:ingress3", "s8:egress7", "s13:ingress6", "s13:egress7"]}, "s21": {"s3": ["s21:ingress7", "s21:egress6", "s8:ingress15", "s8:egress7", "s13:ingress6", "s13:egress7"]}}, "h121": {"s3": {"s12": ["s21:ingress7", "s21:egress1", "s3:ingress15", "s3:egress3", "s9:ingress1", "s9:egress6", "s8:ingress3", "s8:egress6", "s12:ingress6", "s12:egress7"]}, "s21": {"s3": ["s21:ingress7", "s21:egress6", "s8:ingress15", "s8:egress6", "s12:ingress6", "s12:egress7"]}}, "h261": {"s3": {"s26": ["s21:ingress7", "s21:egress1", "s3:ingress15", "s3:egress3", "s9:ingress1", "s9:egress6", "s8:ingress3", "s8:egress20", "s26:ingress6", "s26:egress7"]}, "s21": {"s3": ["s21:ingress7", "s21:egress6", "s8:ingress15", "s8:egress20", "s26:ingress6", "s26:egress7"]}}, "h91": {"s3": {"s9": ["s21:ingress7", "s21:egress1", "s3:ingress15", "s3:egress12", "s18:ingress1", "s18:egress6", "s8:ingress12", "s8:egress3", "s9:ingress6", "s9:egress7"]}, "s21": {"s3": ["s21:ingress7", "s21:egress6", "s8:ingress15", "s8:egress3", "s9:ingress6", "s9:egress7"]}}, "h161": {"s3": {"s16": ["s21:ingress7", "s21:egress1", "s3:ingress15", "s3:egress3", "s9:ingress1", "s9:egress6", "s8:ingress3", "s8:egress10", "s16:ingress6", "s16:egress7"]}, "s21": {"s3": ["s21:ingress7", "s21:egress6", "s8:ingress15", "s8:egress10", "s16:ingress6", "s16:egress7"]}}, "h191": {"s3": {"s19": ["s21:ingress7", "s21:egress1", "s3:ingress15", "s3:egress3", "s9:ingress1", "s9:egress6", "s8:ingress3", "s8:egress13", "s19:ingress6", "s19:egress7"]}, "s21": {"s3": ["s21:ingress7", "s21:egress6", "s8:ingress15", "s8:egress13", "s19:ingress6", "s19:egress7"]}}, "h101": {"s3": {"s10": ["s21:ingress7", "s21:egress1", "s3:ingress15", "s3:egress3", "s9:ingress1", "s9:egress6", "s8:ingress3", "s8:egress4", "s10:ingress6", "s10:egress7"]}, "s21": {"s3": ["s21:ingress7", "s21:egress6", "s8:ingress15", "s8:egress4", "s10:ingress6", "s10:egress7"]}}, "h221": {"s3": {"s22": ["s21:ingress7", "s21:egress1", "s3:ingress15", "s3:egress3", "s9:ingress1", "s9:egress6", "s8:ingress3", "s8:egress16", "s22:ingress6", "s22:egress7"]}, "s21": {"s3": ["s21:ingress7", "s21:egress6", "s8:ingress15", "s8:egress16", "s22:ingress6", "s22:egress7"]}}, "h141": {"s3": {"s14": ["s21:ingress7", "s21:egress1", "s3:ingress15", "s3:egress3", "s9:ingress1", "s9:egress6", "s8:ingress3", "s8:egress8", "s14:ingress6", "s14:egress7"]}, "s21": {"s3": ["s21:ingress7", "s21:egress6", "s8:ingress15", "s8:egress8", "s14:ingress6", "s14:egress7"]}}, "h251": {"s3": {"s25": ["s21:ingress7", "s21:egress1", "s3:ingress15", "s3:egress3", "s9:ingress1", "s9:egress6", "s8:ingress3", "s8:egress19", "s25:ingress6", "s25:egress7"]}, "s21": {"s3": ["s21:ingress7", "s21:egress6", "s8:ingress15", "s8:egress19", "s25:ingress6", "s25:egress7"]}}, "h201": {"s3": {"s20": ["s21:ingress7", "s21:egress1", "s3:ingress15", "s3:egress3", "s9:ingress1", "s9:egress6", "s8:ingress3", "s8:egress14", "s20:ingress6", "s20:egress7"]}, "s21": {"s3": ["s21:ingress7", "s21:egress6", "s8:ingress15", "s8:egress14", "s20:ingress6", "s20:egress7"]}}, "h181": {"s3": {"s18": ["s21:ingress7", "s21:egress1", "s3:ingress15", "s3:egress3", "s9:ingress1", "s9:egress6", "s8:ingress3", "s8:egress12", "s18:ingress6", "s18:egress7"]}, "s21": {"s3": ["s21:ingress7", "s21:egress6", "s8:ingress15", "s8:egress12", "s18:ingress6", "s18:egress7"]}}, "h151": {"s3": {"s15": ["s21:ingress7", "s21:egress1", "s3:ingress15", "s3:egress3", "s9:ingress1", "s9:egress6", "s8:ingress3", "s8:egress9", "s15:ingress6", "s15:egress7"]}, "s21": {"s3": ["s21:ingress7", "s21:egress6", "s8:ingress15", "s8:egress9", "s15:ingress6", "s15:egress7"]}}}, "h151": {"h241": {"s3": {"s24": ["s15:ingress7", "s15:egress1", "s3:ingress9", "s3:egress3", "s9:ingress1", "s9:egress6", "s8:ingress3", "s8:egress18", "s24:ingress6", "s24:egress7"]}, "s15": {"s3": ["s15:ingress7", "s15:egress6", "s8:ingress9", "s8:egress18", "s24:ingress6", "s24:egress7"]}}, "h231": {"s3": {"s23": ["s15:ingress7", "s15:egress1", "s3:ingress9", "s3:egress3", "s9:ingress1", "s9:egress6", "s8:ingress3", "s8:egress17", "s23:ingress6", "s23:egress7"]}, "s15": {"s3": ["s15:ingress7", "s15:egress6", "s8:ingress9", "s8:egress17", "s23:ingress6", "s23:egress7"]}}, "h171": {"s3": {"s17": ["s15:ingress7", "s15:egress1", "s3:ingress9", "s3:egress3", "s9:ingress1", "s9:egress6", "s8:ingress3", "s8:egress11", "s17:ingress6", "s17:egress7"]}, "s15": {"s3": ["s15:ingress7", "s15:egress6", "s8:ingress9", "s8:egress11", "s17:ingress6", "s17:egress7"]}}, "h111": {"s3": {"s11": ["s15:ingress7", "s15:egress1", "s3:ingress9", "s3:egress3", "s9:ingress1", "s9:egress6", "s8:ingress3", "s8:egress5", "s11:ingress6", "s11:egress7"]}, "s15": {"s3": ["s15:ingress7", "s15:egress6", "s8:ingress9", "s8:egress5", "s11:ingress6", "s11:egress7"]}}, "h131": {"s3": {"s13": ["s15:ingress7", "s15:egress1", "s3:ingress9", "s3:egress3", "s9:ingress1", "s9:egress6", "s8:ingress3", "s8:egress7", "s13:ingress6", "s13:egress7"]}, "s15": {"s3": ["s15:ingress7", "s15:egress6", "s8:ingress9", "s8:egress7", "s13:ingress6", "s13:egress7"]}}, "h121": {"s3": {"s12": ["s15:ingress7", "s15:egress1", "s3:ingress9", "s3:egress3", "s9:ingress1", "s9:egress6", "s8:ingress3", "s8:egress6", "s12:ingress6", "s12:egress7"]}, "s15": {"s3": ["s15:ingress7", "s15:egress6", "s8:ingress9", "s8:egress6", "s12:ingress6", "s12:egress7"]}}, "h261": {"s3": {"s26": ["s15:ingress7", "s15:egress1", "s3:ingress9", "s3:egress3", "s9:ingress1", "s9:egress6", "s8:ingress3", "s8:egress20", "s26:ingress6", "s26:egress7"]}, "s15": {"s3": ["s15:ingress7", "s15:egress6", "s8:ingress9", "s8:egress20", "s26:ingress6", "s26:egress7"]}}, "h91": {"s3": {"s9": ["s15:ingress7", "s15:egress1", "s3:ingress9", "s3:egress12", "s18:ingress1", "s18:egress6", "s8:ingress12", "s8:egress3", "s9:ingress6", "s9:egress7"]}, "s15": {"s3": ["s15:ingress7", "s15:egress6", "s8:ingress9", "s8:egress3", "s9:ingress6", "s9:egress7"]}}, "h161": {"s3": {"s16": ["s15:ingress7", "s15:egress1", "s3:ingress9", "s3:egress3", "s9:ingress1", "s9:egress6", "s8:ingress3", "s8:egress10", "s16:ingress6", "s16:egress7"]}, "s15": {"s3": ["s15:ingress7", "s15:egress6", "s8:ingress9", "s8:egress10", "s16:ingress6", "s16:egress7"]}}, "h191": {"s3": {"s19": ["s15:ingress7", "s15:egress1", "s3:ingress9", "s3:egress3", "s9:ingress1", "s9:egress6", "s8:ingress3", "s8:egress13", "s19:ingress6", "s19:egress7"]}, "s15": {"s3": ["s15:ingress7", "s15:egress6", "s8:ingress9", "s8:egress13", "s19:ingress6", "s19:egress7"]}}, "h101": {"s3": {"s10": ["s15:ingress7", "s15:egress1", "s3:ingress9", "s3:egress3", "s9:ingress1", "s9:egress6", "s8:ingress3", "s8:egress4", "s10:ingress6", "s10:egress7"]}, "s15": {"s3": ["s15:ingress7", "s15:egress6", "s8:ingress9", "s8:egress4", "s10:ingress6", "s10:egress7"]}}, "h221": {"s3": {"s22": ["s15:ingress7", "s15:egress1", "s3:ingress9", "s3:egress3", "s9:ingress1", "s9:egress6", "s8:ingress3", "s8:egress16", "s22:ingress6", "s22:egress7"]}, "s15": {"s3": ["s15:ingress7", "s15:egress6", "s8:ingress9", "s8:egress16", "s22:ingress6", "s22:egress7"]}}, "h141": {"s3": {"s14": ["s15:ingress7", "s15:egress1", "s3:ingress9", "s3:egress3", "s9:ingress1", "s9:egress6", "s8:ingress3", "s8:egress8", "s14:ingress6", "s14:egress7"]}, "s15": {"s3": ["s15:ingress7", "s15:egress6", "s8:ingress9", "s8:egress8", "s14:ingress6", "s14:egress7"]}}, "h251": {"s3": {"s25": ["s15:ingress7", "s15:egress1", "s3:ingress9", "s3:egress3", "s9:ingress1", "s9:egress6", "s8:ingress3", "s8:egress19", "s25:ingress6", "s25:egress7"]}, "s15": {"s3": ["s15:ingress7", "s15:egress6", "s8:ingress9", "s8:egress19", "s25:ingress6", "s25:egress7"]}}, "h181": {"s3": {"s18": ["s15:ingress7", "s15:egress1", "s3:ingress9", "s3:egress3", "s9:ingress1", "s9:egress6", "s8:ingress3", "s8:egress12", "s18:ingress6", "s18:egress7"]}, "s15": {"s3": ["s15:ingress7", "s15:egress6", "s8:ingress9", "s8:egress12", "s18:ingress6", "s18:egress7"]}}, "h211": {"s3": {"s21": ["s15:ingress7", "s15:egress1", "s3:ingress9", "s3:egress3", "s9:ingress1", "s9:egress6", "s8:ingress3", "s8:egress15", "s21:ingress6", "s21:egress7"]}, "s15": {"s3": ["s15:ingress7", "s15:egress6", "s8:ingress9", "s8:egress15", "s21:ingress6", "s21:egress7"]}}, "h201": {"s3": {"s20": ["s15:ingress7", "s15:egress1", "s3:ingress9", "s3:egress3", "s9:ingress1", "s9:egress6", "s8:ingress3", "s8:egress14", "s20:ingress6", "s20:egress7"]}, "s15": {"s3": ["s15:ingress7", "s15:egress6", "s8:ingress9", "s8:egress14", "s20:ingress6", "s20:egress7"]}}}}