{"1": {"ports": [{"hw_addr": "ea:6b:31:3f:f8:5c", "curr_speed": 10000000, "curr": 2112, "name": "s1-eth3", "supported": 0, "state": 0, "max_speed": 0, "advertised": 0, "peer": 0, "config": 0, "port_no": 3}, {"hw_addr": "a6:51:7b:52:3f:b5", "curr_speed": 10000000, "curr": 2112, "name": "s1-eth1", "supported": 0, "state": 0, "max_speed": 0, "advertised": 0, "peer": 0, "config": 0, "port_no": 1}, {"hw_addr": "9a:f7:33:81:47:0a", "curr_speed": 10000000, "curr": 2112, "name": "s1-eth2", "supported": 0, "state": 0, "max_speed": 0, "advertised": 0, "peer": 0, "config": 0, "port_no": 2}, {"hw_addr": "9e:39:6a:f4:81:48", "curr_speed": 0, "curr": 0, "name": "s1", "supported": 0, "state": 0, "max_speed": 0, "advertised": 0, "peer": 0, "config": 0, "port_no": 4294967294}], "groups": [], "flow_tables": {"0": [{"priority": 1, "duration_sec": 1, "hard_timeout": 0, "byte_count": 342, "length": 64, "duration_nsec": 240000000, "packet_count": 1, "idle_timeout": 0, "cookie": 0, "flags": 0, "table_id": 0, "match": {"dl_type": 2048}, "instructions": {}}, {"priority": 1, "duration_sec": 1, "hard_timeout": 0, "byte_count": 0, "length": 88, "duration_nsec": 240000000, "packet_count": 0, "idle_timeout": 0, "cookie": 0, "flags": 0, "table_id": 0, "match": {"dl_type": 2054}, "instructions": {"APPLY_ACTIONS": ["OUTPUT:4294967293"]}}, {"priority": 0, "duration_sec": 1, "hard_timeout": 0, "byte_count": 1016, "length": 64, "duration_nsec": 240000000, "packet_count": 7, "idle_timeout": 0, "cookie": 0, "flags": 0, "table_id": 0, "match": {}, "instructions": {"GOTO_TABLE": "1"}}]}}, "2": {"ports": [{"hw_addr": "e6:c6:04:a5:76:a0", "curr_speed": 10000000, "curr": 2112, "name": "s2-eth3", "supported": 0, "state": 0, "max_speed": 0, "advertised": 0, "peer": 0, "config": 0, "port_no": 3}, {"hw_addr": "8e:9b:18:e1:ca:ed", "curr_speed": 10000000, "curr": 2112, "name": "s2-eth1", "supported": 0, "state": 0, "max_speed": 0, "advertised": 0, "peer": 0, "config": 0, "port_no": 1}, {"hw_addr": "de:f5:6d:47:5f:6a", "curr_speed": 10000000, "curr": 2112, "name": "s2-eth2", "supported": 0, "state": 0, "max_speed": 0, "advertised": 0, "peer": 0, "config": 0, "port_no": 2}, {"hw_addr": "e2:7f:45:9c:11:46", "curr_speed": 0, "curr": 0, "name": "s2", "supported": 0, "state": 0, "max_speed": 0, "advertised": 0, "peer": 0, "config": 0, "port_no": 4294967294}], "groups": [], "flow_tables": {"0": [{"priority": 1, "duration_sec": 1, "hard_timeout": 0, "byte_count": 0, "length": 64, "duration_nsec": 199000000, "packet_count": 0, "idle_timeout": 0, "cookie": 0, "flags": 0, "table_id": 0, "match": {"dl_type": 2048}, "instructions": {}}, {"priority": 1, "duration_sec": 1, "hard_timeout": 0, "byte_count": 0, "length": 88, "duration_nsec": 200000000, "packet_count": 0, "idle_timeout": 0, "cookie": 0, "flags": 0, "table_id": 0, "match": {"dl_type": 2054}, "instructions": {"APPLY_ACTIONS": ["OUTPUT:4294967293"]}}, {"priority": 0, "duration_sec": 1, "hard_timeout": 0, "byte_count": 1182, "length": 64, "duration_nsec": 199000000, "packet_count": 7, "idle_timeout": 0, "cookie": 0, "flags": 0, "table_id": 0, "match": {}, "instructions": {"GOTO_TABLE": "1"}}]}}, "3": {"ports": [{"hw_addr": "06:f3:7c:7b:74:52", "curr_speed": 10000000, "curr": 2112, "name": "s3-eth3", "supported": 0, "state": 0, "max_speed": 0, "advertised": 0, "peer": 0, "config": 0, "port_no": 3}, {"hw_addr": "fa:5d:f1:e1:a2:4b", "curr_speed": 10000000, "curr": 2112, "name": "s3-eth1", "supported": 0, "state": 0, "max_speed": 0, "advertised": 0, "peer": 0, "config": 0, "port_no": 1}, {"hw_addr": "32:ee:56:4c:32:ed", "curr_speed": 10000000, "curr": 2112, "name": "s3-eth2", "supported": 0, "state": 0, "max_speed": 0, "advertised": 0, "peer": 0, "config": 0, "port_no": 2}, {"hw_addr": "82:5d:c2:95:b0:4c", "curr_speed": 0, "curr": 0, "name": "s3", "supported": 0, "state": 0, "max_speed": 0, "advertised": 0, "peer": 0, "config": 0, "port_no": 4294967294}], "groups": [], "flow_tables": {"0": [{"priority": 1, "duration_sec": 1, "hard_timeout": 0, "byte_count": 342, "length": 64, "duration_nsec": 159000000, "packet_count": 1, "idle_timeout": 0, "cookie": 0, "flags": 0, "table_id": 0, "match": {"dl_type": 2048}, "instructions": {}}, {"priority": 1, "duration_sec": 1, "hard_timeout": 0, "byte_count": 0, "length": 88, "duration_nsec": 161000000, "packet_count": 0, "idle_timeout": 0, "cookie": 0, "flags": 0, "table_id": 0, "match": {"dl_type": 2054}, "instructions": {"APPLY_ACTIONS": ["OUTPUT:4294967293"]}}, {"priority": 0, "duration_sec": 1, "hard_timeout": 0, "byte_count": 2505, "length": 64, "duration_nsec": 158000000, "packet_count": 17, "idle_timeout": 0, "cookie": 0, "flags": 0, "table_id": 0, "match": {}, "instructions": {"GOTO_TABLE": "1"}}]}}, "4": {"ports": [{"hw_addr": "c6:9a:a3:99:90:58", "curr_speed": 10000000, "curr": 2112, "name": "s4-eth3", "supported": 0, "state": 0, "max_speed": 0, "advertised": 0, "peer": 0, "config": 0, "port_no": 3}, {"hw_addr": "6a:59:e6:7a:ef:18", "curr_speed": 10000000, "curr": 2112, "name": "s4-eth1", "supported": 0, "state": 0, "max_speed": 0, "advertised": 0, "peer": 0, "config": 0, "port_no": 1}, {"hw_addr": "de:3b:d8:3d:5e:2e", "curr_speed": 10000000, "curr": 2112, "name": "s4-eth2", "supported": 0, "state": 0, "max_speed": 0, "advertised": 0, "peer": 0, "config": 0, "port_no": 2}, {"hw_addr": "92:7d:77:ee:4d:46", "curr_speed": 0, "curr": 0, "name": "s4", "supported": 0, "state": 0, "max_speed": 0, "advertised": 0, "peer": 0, "config": 0, "port_no": 4294967294}], "groups": [], "flow_tables": {"0": [{"priority": 1, "duration_sec": 1, "hard_timeout": 0, "byte_count": 342, "length": 64, "duration_nsec": 142000000, "packet_count": 1, "idle_timeout": 0, "cookie": 0, "flags": 0, "table_id": 0, "match": {"dl_type": 2048}, "instructions": {}}, {"priority": 1, "duration_sec": 1, "hard_timeout": 0, "byte_count": 0, "length": 88, "duration_nsec": 143000000, "packet_count": 0, "idle_timeout": 0, "cookie": 0, "flags": 0, "table_id": 0, "match": {"dl_type": 2054}, "instructions": {"APPLY_ACTIONS": ["OUTPUT:4294967293"]}}, {"priority": 0, "duration_sec": 1, "hard_timeout": 0, "byte_count": 1654, "length": 64, "duration_nsec": 142000000, "packet_count": 13, "idle_timeout": 0, "cookie": 0, "flags": 0, "table_id": 0, "match": {}, "instructions": {"GOTO_TABLE": "1"}}]}}}